Workbook

Sheet CONTROLE
A1: INIBANK | B1: INICIATIVA | C1: Tipo | D1: Prestadora | E1: Matrícula | F1: Nome | G1: Projeção 2026 | H1: 46023 | I1: 46054 | J1: 46082 | K1: 46113 | L1: 46143 | M1: 46174 | N1: 46204 | O1: 46235 | P1: 46266 | Q1: 46296 | R1: 46327 | S1: 46357
A2: INIBANK-611 | B2: Implantação do SalesForce para Central de Atendimento de Clientes PJ | C2: Forecast | G2: =SUM(H2:S2) -> 0 | H2: 0 | I2: 0 | J2: 0 | K2: 0 | L2: 0 | M2: 0 | N2: 0 | O2: 0 | P2: 0 | Q2: 0 | R2: 0 | S2: 0
A3: INIBANK-289 | B3: Sustentação Atendimento Salesforce Odin | C3: Forecast | G3: =SUM(H3:S3) -> 0 | H3: 0 | I3: 0 | J3: 0 | K3: 0 | L3: 0 | M3: 0 | N3: 0 | O3: 0 | P3: 0 | Q3: 0 | R3: 0 | S3: 0
A4: INIBANK-1417 | B4: [Sustentação] Atendimento / Salesforce | C4: Forecast | G4: =SUM(H4:S4) -> 1865718 | H4: 155476.5 | I4: 155476.5 | J4: 155476.5 | K4: 155476.5 | L4: 155476.5 | M4: 155476.5 | N4: 155476.5 | O4: 155476.5 | P4: 155476.5 | Q4: 155476.5 | R4: 155476.5 | S4: 155476.5
A5: INIBANK-1173 | B5: [Book] Squad Salesforce (Atendimento) | C5: Forecast | G5: =SUM(H5:S5) -> 3955366 | H5: =329613.833333333 -> 329613.83 | I5: 329613.83 | J5: 329613.83 | K5: 329613.83 | L5: 329613.83 | M5: 329613.83 | N5: 329613.83 | O5: 329613.83 | P5: 329613.83 | Q5: 329613.83 | R5: 329613.83 | S5: 329613.83
A6: INIBANK-1349 | B6: Atendimento INVEST BANK | C6: Forecast | G6: =SUM(H6:S6) -> 100000 | H6: 56033.94 | I6: 0 | J6: 43966.06 | K6: 0 | L6: 0 | M6: 0 | N6: 0 | O6: 0 | P6: 0 | Q6: 0 | R6: 0 | S6: 0
A8: INIBANK-1173 | B8: [Book] Squad Salesforce (Atendimento) | C8: Time Alocado | D8: Sys4B | E8: P0660057 | F8: Cleiton Lima de Jesus | G8: =SUM(H8:S8) -> 482760.96 | H8: =VLOOKUP($E8,'ORÇAMENTO 2026 v3'!$D:$X,8,0) -> 40230.08 | I8: =VLOOKUP($E8,'ORÇAMENTO 2026 v3'!$D:$X,9,0) -> 40230.08 | J8: =VLOOKUP($E8,'ORÇAMENTO 2026 v3'!$D:$X,10,0) -> 40230.08 | K8: =VLOOKUP($E8,'ORÇAMENTO 2026 v3'!$D:$X,11,0) -> 40230.08 | L8: =VLOOKUP($E8,'ORÇAMENTO 2026 v3'!$D:$X,12,0) -> 40230.08 | M8: =VLOOKUP($E8,'ORÇAMENTO 2026 v3'!$D:$X,13,0) -> 40230.08 | N8: =VLOOKUP($E8,'ORÇAMENTO 2026 v3'!$D:$X,14,0) -> 40230.08 | O8: =VLOOKUP($E8,'ORÇAMENTO 2026 v3'!$D:$X,15,0) -> 40230.08 | P8: =VLOOKUP($E8,'ORÇAMENTO 2026 v3'!$D:$X,16,0) -> 40230.08 | Q8: =VLOOKUP($E8,'ORÇAMENTO 2026 v3'!$D:$X,17,0) -> 40230.08 | R8: =VLOOKUP($E8,'ORÇAMENTO 2026 v3'!$D:$X,18,0) -> 40230.08 | S8: =VLOOKUP($E8,'ORÇAMENTO 2026 v3'!$D:$X,19,0) -> 40230.08
A9: INIBANK-1173 | B9: [Book] Squad Salesforce (Atendimento) | C9: Time Alocado | D9: Sys4B | E9: P0656797 | F9: Gustavo Seiji Onizuka | G9: =SUM(H9:S9) -> 451693.44 | H9: =VLOOKUP($E9,'ORÇAMENTO 2026 v3'!$D:$X,8,0) -> 37641.12 | I9: =VLOOKUP($E9,'ORÇAMENTO 2026 v3'!$D:$X,9,0) -> 37641.12 | J9: =VLOOKUP($E9,'ORÇAMENTO 2026 v3'!$D:$X,10,0) -> 37641.12 | K9: =VLOOKUP($E9,'ORÇAMENTO 2026 v3'!$D:$X,11,0) -> 37641.12 | L9: =VLOOKUP($E9,'ORÇAMENTO 2026 v3'!$D:$X,12,0) -> 37641.12 | M9: =VLOOKUP($E9,'ORÇAMENTO 2026 v3'!$D:$X,13,0) -> 37641.12 | N9: =VLOOKUP($E9,'ORÇAMENTO 2026 v3'!$D:$X,14,0) -> 37641.12 | O9: =VLOOKUP($E9,'ORÇAMENTO 2026 v3'!$D:$X,15,0) -> 37641.12 | P9: =VLOOKUP($E9,'ORÇAMENTO 2026 v3'!$D:$X,16,0) -> 37641.12 | Q9: =VLOOKUP($E9,'ORÇAMENTO 2026 v3'!$D:$X,17,0) -> 37641.12 | R9: =VLOOKUP($E9,'ORÇAMENTO 2026 v3'!$D:$X,18,0) -> 37641.12 | S9: =VLOOKUP($E9,'ORÇAMENTO 2026 v3'!$D:$X,19,0) -> 37641.12
A10: INIBANK-1173 | B10: [Book] Squad Salesforce (Atendimento) | C10: Time Alocado | D10: Sys4B | E10: P0658519 | F10: Leonardo Lins | G10: =SUM(H10:S10) -> 451693.44 | H10: =VLOOKUP($E10,'ORÇAMENTO 2026 v3'!$D:$X,8,0) -> 37641.12 | I10: =VLOOKUP($E10,'ORÇAMENTO 2026 v3'!$D:$X,9,0) -> 37641.12 | J10: =VLOOKUP($E10,'ORÇAMENTO 2026 v3'!$D:$X,10,0) -> 37641.12 | K10: =VLOOKUP($E10,'ORÇAMENTO 2026 v3'!$D:$X,11,0) -> 37641.12 | L10: =VLOOKUP($E10,'ORÇAMENTO 2026 v3'!$D:$X,12,0) -> 37641.12 | M10: =VLOOKUP($E10,'ORÇAMENTO 2026 v3'!$D:$X,13,0) -> 37641.12 | N10: =VLOOKUP($E10,'ORÇAMENTO 2026 v3'!$D:$X,14,0) -> 37641.12 | O10: =VLOOKUP($E10,'ORÇAMENTO 2026 v3'!$D:$X,15,0) -> 37641.12 | P10: =VLOOKUP($E10,'ORÇAMENTO 2026 v3'!$D:$X,16,0) -> 37641.12 | Q10: =VLOOKUP($E10,'ORÇAMENTO 2026 v3'!$D:$X,17,0) -> 37641.12 | R10: =VLOOKUP($E10,'ORÇAMENTO 2026 v3'!$D:$X,18,0) -> 37641.12 | S10: =VLOOKUP($E10,'ORÇAMENTO 2026 v3'!$D:$X,19,0) -> 37641.12
A11: INIBANK-1173 | B11: [Book] Squad Salesforce (Atendimento) | C11: Time Alocado | D11: Sys4B | E11: P0654694 | F11: Carlos Eduardo Santos Santana | G11: =SUM(H11:S11) -> 451693.44 | H11: =VLOOKUP($E11,'ORÇAMENTO 2026 v3'!$D:$X,8,0) -> 37641.12 | I11: =VLOOKUP($E11,'ORÇAMENTO 2026 v3'!$D:$X,9,0) -> 37641.12 | J11: =VLOOKUP($E11,'ORÇAMENTO 2026 v3'!$D:$X,10,0) -> 37641.12 | K11: =VLOOKUP($E11,'ORÇAMENTO 2026 v3'!$D:$X,11,0) -> 37641.12 | L11: =VLOOKUP($E11,'ORÇAMENTO 2026 v3'!$D:$X,12,0) -> 37641.12 | M11: =VLOOKUP($E11,'ORÇAMENTO 2026 v3'!$D:$X,13,0) -> 37641.12 | N11: =VLOOKUP($E11,'ORÇAMENTO 2026 v3'!$D:$X,14,0) -> 37641.12 | O11: =VLOOKUP($E11,'ORÇAMENTO 2026 v3'!$D:$X,15,0) -> 37641.12 | P11: =VLOOKUP($E11,'ORÇAMENTO 2026 v3'!$D:$X,16,0) -> 37641.12 | Q11: =VLOOKUP($E11,'ORÇAMENTO 2026 v3'!$D:$X,17,0) -> 37641.12 | R11: =VLOOKUP($E11,'ORÇAMENTO 2026 v3'!$D:$X,18,0) -> 37641.12 | S11: =VLOOKUP($E11,'ORÇAMENTO 2026 v3'!$D:$X,19,0) -> 37641.12
A12: INIBANK-1173 | B12: [Book] Squad Salesforce (Atendimento) | C12: Time Alocado | D12: Capgemini | E12: P0661574 | F12: Leonardo Lassance | G12: =SUM(H12:S12) -> 633093.12 | H12: =VLOOKUP($E12,'ORÇAMENTO 2026 v3'!$D:$X,8,0) -> 52757.76 | I12: =VLOOKUP($E12,'ORÇAMENTO 2026 v3'!$D:$X,9,0) -> 52757.76 | J12: =VLOOKUP($E12,'ORÇAMENTO 2026 v3'!$D:$X,10,0) -> 52757.76 | K12: =VLOOKUP($E12,'ORÇAMENTO 2026 v3'!$D:$X,11,0) -> 52757.76 | L12: =VLOOKUP($E12,'ORÇAMENTO 2026 v3'!$D:$X,12,0) -> 52757.76 | M12: =VLOOKUP($E12,'ORÇAMENTO 2026 v3'!$D:$X,13,0) -> 52757.76 | N12: =VLOOKUP($E12,'ORÇAMENTO 2026 v3'!$D:$X,14,0) -> 52757.76 | O12: =VLOOKUP($E12,'ORÇAMENTO 2026 v3'!$D:$X,15,0) -> 52757.76 | P12: =VLOOKUP($E12,'ORÇAMENTO 2026 v3'!$D:$X,16,0) -> 52757.76 | Q12: =VLOOKUP($E12,'ORÇAMENTO 2026 v3'!$D:$X,17,0) -> 52757.76 | R12: =VLOOKUP($E12,'ORÇAMENTO 2026 v3'!$D:$X,18,0) -> 52757.76 | S12: =VLOOKUP($E12,'ORÇAMENTO 2026 v3'!$D:$X,19,0) -> 52757.76
A13: INIBANK-1173 | B13: [Book] Squad Salesforce (Atendimento) | C13: Time Alocado | D13: Capgemini | E13: P0661361 | F13: Fernando da Silva Trevisan | G13: =SUM(H13:S13) -> 611107.2 | H13: =VLOOKUP($E13,'ORÇAMENTO 2026 v3'!$D:$X,8,0) -> 50925.6 | I13: =VLOOKUP($E13,'ORÇAMENTO 2026 v3'!$D:$X,9,0) -> 50925.6 | J13: =VLOOKUP($E13,'ORÇAMENTO 2026 v3'!$D:$X,10,0) -> 50925.6 | K13: =VLOOKUP($E13,'ORÇAMENTO 2026 v3'!$D:$X,11,0) -> 50925.6 | L13: =VLOOKUP($E13,'ORÇAMENTO 2026 v3'!$D:$X,12,0) -> 50925.6 | M13: =VLOOKUP($E13,'ORÇAMENTO 2026 v3'!$D:$X,13,0) -> 50925.6 | N13: =VLOOKUP($E13,'ORÇAMENTO 2026 v3'!$D:$X,14,0) -> 50925.6 | O13: =VLOOKUP($E13,'ORÇAMENTO 2026 v3'!$D:$X,15,0) -> 50925.6 | P13: =VLOOKUP($E13,'ORÇAMENTO 2026 v3'!$D:$X,16,0) -> 50925.6 | Q13: =VLOOKUP($E13,'ORÇAMENTO 2026 v3'!$D:$X,17,0) -> 50925.6 | R13: =VLOOKUP($E13,'ORÇAMENTO 2026 v3'!$D:$X,18,0) -> 50925.6 | S13: =VLOOKUP($E13,'ORÇAMENTO 2026 v3'!$D:$X,19,0) -> 50925.6
A14: INIBANK-1173 | B14: [Book] Squad Salesforce (Atendimento) | C14: Time Alocado | D14: Capgemini | E14: P0661715 | F14: Marcel Vallim Moreira | G14: =SUM(H14:S14) -> 427933.44 | H14: =VLOOKUP($E14,'ORÇAMENTO 2026 v3'!$D:$X,8,0) -> 35661.12 | I14: =VLOOKUP($E14,'ORÇAMENTO 2026 v3'!$D:$X,9,0) -> 35661.12 | J14: =VLOOKUP($E14,'ORÇAMENTO 2026 v3'!$D:$X,10,0) -> 35661.12 | K14: =VLOOKUP($E14,'ORÇAMENTO 2026 v3'!$D:$X,11,0) -> 35661.12 | L14: =VLOOKUP($E14,'ORÇAMENTO 2026 v3'!$D:$X,12,0) -> 35661.12 | M14: =VLOOKUP($E14,'ORÇAMENTO 2026 v3'!$D:$X,13,0) -> 35661.12 | N14: =VLOOKUP($E14,'ORÇAMENTO 2026 v3'!$D:$X,14,0) -> 35661.12 | O14: =VLOOKUP($E14,'ORÇAMENTO 2026 v3'!$D:$X,15,0) -> 35661.12 | P14: =VLOOKUP($E14,'ORÇAMENTO 2026 v3'!$D:$X,16,0) -> 35661.12 | Q14: =VLOOKUP($E14,'ORÇAMENTO 2026 v3'!$D:$X,17,0) -> 35661.12 | R14: =VLOOKUP($E14,'ORÇAMENTO 2026 v3'!$D:$X,18,0) -> 35661.12 | S14: =VLOOKUP($E14,'ORÇAMENTO 2026 v3'!$D:$X,19,0) -> 35661.12
A15: INIBANK-1173 | B15: [Book] Squad Salesforce (Atendimento) | C15: Time Alocado | D15: Capgemini | E15: P0661738 | F15: Erick Delfino Silva | G15: =SUM(H15:S15) -> 409178.88 | H15: =VLOOKUP($E15,'ORÇAMENTO 2026 v3'!$D:$X,8,0) -> 34098.24 | I15: =VLOOKUP($E15,'ORÇAMENTO 2026 v3'!$D:$X,9,0) -> 34098.24 | J15: =VLOOKUP($E15,'ORÇAMENTO 2026 v3'!$D:$X,10,0) -> 34098.24 | K15: =VLOOKUP($E15,'ORÇAMENTO 2026 v3'!$D:$X,11,0) -> 34098.24 | L15: =VLOOKUP($E15,'ORÇAMENTO 2026 v3'!$D:$X,12,0) -> 34098.24 | M15: =VLOOKUP($E15,'ORÇAMENTO 2026 v3'!$D:$X,13,0) -> 34098.24 | N15: =VLOOKUP($E15,'ORÇAMENTO 2026 v3'!$D:$X,14,0) -> 34098.24 | O15: =VLOOKUP($E15,'ORÇAMENTO 2026 v3'!$D:$X,15,0) -> 34098.24 | P15: =VLOOKUP($E15,'ORÇAMENTO 2026 v3'!$D:$X,16,0) -> 34098.24 | Q15: =VLOOKUP($E15,'ORÇAMENTO 2026 v3'!$D:$X,17,0) -> 34098.24 | R15: =VLOOKUP($E15,'ORÇAMENTO 2026 v3'!$D:$X,18,0) -> 34098.24 | S15: =VLOOKUP($E15,'ORÇAMENTO 2026 v3'!$D:$X,19,0) -> 34098.24
A16: INIBANK-1417 | B16: [Sustentação] Atendimento / Salesforce | C16: Time Alocado | D16: Sys4B | E16: P0662312 | F16: Francielle Thiezo Revesso Pinto | G16: =SUM(H16:S16) -> 451693.44 | H16: =VLOOKUP($E16,'ORÇAMENTO 2026 v3'!$D:$X,8,0) -> 37641.12 | I16: =VLOOKUP($E16,'ORÇAMENTO 2026 v3'!$D:$X,9,0) -> 37641.12 | J16: =VLOOKUP($E16,'ORÇAMENTO 2026 v3'!$D:$X,10,0) -> 37641.12 | K16: =VLOOKUP($E16,'ORÇAMENTO 2026 v3'!$D:$X,11,0) -> 37641.12 | L16: =VLOOKUP($E16,'ORÇAMENTO 2026 v3'!$D:$X,12,0) -> 37641.12 | M16: =VLOOKUP($E16,'ORÇAMENTO 2026 v3'!$D:$X,13,0) -> 37641.12 | N16: =VLOOKUP($E16,'ORÇAMENTO 2026 v3'!$D:$X,14,0) -> 37641.12 | O16: =VLOOKUP($E16,'ORÇAMENTO 2026 v3'!$D:$X,15,0) -> 37641.12 | P16: =VLOOKUP($E16,'ORÇAMENTO 2026 v3'!$D:$X,16,0) -> 37641.12 | Q16: =VLOOKUP($E16,'ORÇAMENTO 2026 v3'!$D:$X,17,0) -> 37641.12 | R16: =VLOOKUP($E16,'ORÇAMENTO 2026 v3'!$D:$X,18,0) -> 37641.12 | S16: =VLOOKUP($E16,'ORÇAMENTO 2026 v3'!$D:$X,19,0) -> 37641.12
A17: INIBANK-1417 | B17: [Sustentação] Atendimento / Salesforce | C17: Time Alocado | D17: Sys4B | E17: P0650648 | F17: Lucas Takita | G17: =SUM(H17:S17) -> 451693.44 | H17: =VLOOKUP($E17,'ORÇAMENTO 2026 v3'!$D:$X,8,0) -> 37641.12 | I17: =VLOOKUP($E17,'ORÇAMENTO 2026 v3'!$D:$X,9,0) -> 37641.12 | J17: =VLOOKUP($E17,'ORÇAMENTO 2026 v3'!$D:$X,10,0) -> 37641.12 | K17: =VLOOKUP($E17,'ORÇAMENTO 2026 v3'!$D:$X,11,0) -> 37641.12 | L17: =VLOOKUP($E17,'ORÇAMENTO 2026 v3'!$D:$X,12,0) -> 37641.12 | M17: =VLOOKUP($E17,'ORÇAMENTO 2026 v3'!$D:$X,13,0) -> 37641.12 | N17: =VLOOKUP($E17,'ORÇAMENTO 2026 v3'!$D:$X,14,0) -> 37641.12 | O17: =VLOOKUP($E17,'ORÇAMENTO 2026 v3'!$D:$X,15,0) -> 37641.12 | P17: =VLOOKUP($E17,'ORÇAMENTO 2026 v3'!$D:$X,16,0) -> 37641.12 | Q17: =VLOOKUP($E17,'ORÇAMENTO 2026 v3'!$D:$X,17,0) -> 37641.12 | R17: =VLOOKUP($E17,'ORÇAMENTO 2026 v3'!$D:$X,18,0) -> 37641.12 | S17: =VLOOKUP($E17,'ORÇAMENTO 2026 v3'!$D:$X,19,0) -> 37641.12
A18: INIBANK-1417 | B18: [Sustentação] Atendimento / Salesforce | C18: Time Alocado | D18: Sys4B | E18: P0663654 | F18: Gabriel Costa Datovo Inoue Maekawa | G18: =SUM(H18:S18) -> 404152.32 | H18: =VLOOKUP($E18,'ORÇAMENTO 2026 v3'!$D:$X,8,0) -> 33679.36 | I18: =VLOOKUP($E18,'ORÇAMENTO 2026 v3'!$D:$X,9,0) -> 33679.36 | J18: =VLOOKUP($E18,'ORÇAMENTO 2026 v3'!$D:$X,10,0) -> 33679.36 | K18: =VLOOKUP($E18,'ORÇAMENTO 2026 v3'!$D:$X,11,0) -> 33679.36 | L18: =VLOOKUP($E18,'ORÇAMENTO 2026 v3'!$D:$X,12,0) -> 33679.36 | M18: =VLOOKUP($E18,'ORÇAMENTO 2026 v3'!$D:$X,13,0) -> 33679.36 | N18: =VLOOKUP($E18,'ORÇAMENTO 2026 v3'!$D:$X,14,0) -> 33679.36 | O18: =VLOOKUP($E18,'ORÇAMENTO 2026 v3'!$D:$X,15,0) -> 33679.36 | P18: =VLOOKUP($E18,'ORÇAMENTO 2026 v3'!$D:$X,16,0) -> 33679.36 | Q18: =VLOOKUP($E18,'ORÇAMENTO 2026 v3'!$D:$X,17,0) -> 33679.36 | R18: =VLOOKUP($E18,'ORÇAMENTO 2026 v3'!$D:$X,18,0) -> 33679.36 | S18: =VLOOKUP($E18,'ORÇAMENTO 2026 v3'!$D:$X,19,0) -> 33679.36
A19: INIBANK-1417 | B19: [Sustentação] Atendimento / Salesforce | C19: Time Alocado | D19: Sys4B | E19: P0000000 | F19: Plantão Salesforce Odin | G19: =SUM(H19:S19) -> 480000 | H19: =VLOOKUP($E19,'ORÇAMENTO 2026 v3'!$D:$X,8,0) -> 40000 | I19: =VLOOKUP($E19,'ORÇAMENTO 2026 v3'!$D:$X,9,0) -> 40000 | J19: =VLOOKUP($E19,'ORÇAMENTO 2026 v3'!$D:$X,10,0) -> 40000 | K19: =VLOOKUP($E19,'ORÇAMENTO 2026 v3'!$D:$X,11,0) -> 40000 | L19: =VLOOKUP($E19,'ORÇAMENTO 2026 v3'!$D:$X,12,0) -> 40000 | M19: =VLOOKUP($E19,'ORÇAMENTO 2026 v3'!$D:$X,13,0) -> 40000 | N19: =VLOOKUP($E19,'ORÇAMENTO 2026 v3'!$D:$X,14,0) -> 40000 | O19: =VLOOKUP($E19,'ORÇAMENTO 2026 v3'!$D:$X,15,0) -> 40000 | P19: =VLOOKUP($E19,'ORÇAMENTO 2026 v3'!$D:$X,16,0) -> 40000 | Q19: =VLOOKUP($E19,'ORÇAMENTO 2026 v3'!$D:$X,17,0) -> 40000 | R19: =VLOOKUP($E19,'ORÇAMENTO 2026 v3'!$D:$X,18,0) -> 40000 | S19: =VLOOKUP($E19,'ORÇAMENTO 2026 v3'!$D:$X,19,0) -> 40000
A21: INIBANK-611 | B21: Implantação do SalesForce para Central de Atendimento de Clientes PJ | C21: Realizado | G21: =SUM(H21:S21) -> 252716.37 | H21: =SUMIFS(NOTA_FISCAL_ANALITICO!$G:$G,NOTA_FISCAL_ANALITICO!$D:$D,CONTROLE!H$1,NOTA_FISCAL_ANALITICO!$J:$J,CONTROLE!$A21) -> 252716.37 | I21: =SUMIFS(NOTA_FISCAL_ANALITICO!$G:$G,NOTA_FISCAL_ANALITICO!$D:$D,CONTROLE!I$1,NOTA_FISCAL_ANALITICO!$J:$J,CONTROLE!$A21) -> 0 | J21: =SUMIFS(NOTA_FISCAL_ANALITICO!$G:$G,NOTA_FISCAL_ANALITICO!$D:$D,CONTROLE!J$1,NOTA_FISCAL_ANALITICO!$J:$J,CONTROLE!$A21) -> 0 | K21: =SUMIFS(NOTA_FISCAL_ANALITICO!$G:$G,NOTA_FISCAL_ANALITICO!$D:$D,CONTROLE!K$1,NOTA_FISCAL_ANALITICO!$J:$J,CONTROLE!$A21) -> 0 | L21: =SUMIFS(NOTA_FISCAL_ANALITICO!$G:$G,NOTA_FISCAL_ANALITICO!$D:$D,CONTROLE!L$1,NOTA_FISCAL_ANALITICO!$J:$J,CONTROLE!$A21) -> 0 | M21: =SUMIFS(NOTA_FISCAL_ANALITICO!$G:$G,NOTA_FISCAL_ANALITICO!$D:$D,CONTROLE!M$1,NOTA_FISCAL_ANALITICO!$J:$J,CONTROLE!$A21) -> 0 | N21: =SUMIFS(NOTA_FISCAL_ANALITICO!$G:$G,NOTA_FISCAL_ANALITICO!$D:$D,CONTROLE!N$1,NOTA_FISCAL_ANALITICO!$J:$J,CONTROLE!$A21) -> 0 | O21: =SUMIFS(NOTA_FISCAL_ANALITICO!$G:$G,NOTA_FISCAL_ANALITICO!$D:$D,CONTROLE!O$1,NOTA_FISCAL_ANALITICO!$J:$J,CONTROLE!$A21) -> 0 | ... S21: =SUMIFS(NOTA_FISCAL_ANALITICO!$G:$G,NOTA_FISCAL_ANALITICO!$D:$D,CONTROLE!S$1,NOTA_FISCAL_ANALITICO!$J:$J,CONTROLE!$A21) -> 0
A22: INIBANK-289 | B22: Sustentação Atendimento Salesforce Odin | C22: Realizado | G22: =SUM(H22:S22) -> 0 | H22: =SUMIFS(NOTA_FISCAL_ANALITICO!$G:$G,NOTA_FISCAL_ANALITICO!$D:$D,CONTROLE!H$1,NOTA_FISCAL_ANALITICO!$J:$J,CONTROLE!$A22) -> 0 | I22: =SUMIFS(NOTA_FISCAL_ANALITICO!$G:$G,NOTA_FISCAL_ANALITICO!$D:$D,CONTROLE!I$1,NOTA_FISCAL_ANALITICO!$J:$J,CONTROLE!$A22) -> 0 | J22: =SUMIFS(NOTA_FISCAL_ANALITICO!$G:$G,NOTA_FISCAL_ANALITICO!$D:$D,CONTROLE!J$1,NOTA_FISCAL_ANALITICO!$J:$J,CONTROLE!$A22) -> 0 | K22: =SUMIFS(NOTA_FISCAL_ANALITICO!$G:$G,NOTA_FISCAL_ANALITICO!$D:$D,CONTROLE!K$1,NOTA_FISCAL_ANALITICO!$J:$J,CONTROLE!$A22) -> 0 | L22: =SUMIFS(NOTA_FISCAL_ANALITICO!$G:$G,NOTA_FISCAL_ANALITICO!$D:$D,CONTROLE!L$1,NOTA_FISCAL_ANALITICO!$J:$J,CONTROLE!$A22) -> 0 | M22: =SUMIFS(NOTA_FISCAL_ANALITICO!$G:$G,NOTA_FISCAL_ANALITICO!$D:$D,CONTROLE!M$1,NOTA_FISCAL_ANALITICO!$J:$J,CONTROLE!$A22) -> 0 | N22: =SUMIFS(NOTA_FISCAL_ANALITICO!$G:$G,NOTA_FISCAL_ANALITICO!$D:$D,CONTROLE!N$1,NOTA_FISCAL_ANALITICO!$J:$J,CONTROLE!$A22) -> 0 | O22: =SUMIFS(NOTA_FISCAL_ANALITICO!$G:$G,NOTA_FISCAL_ANALITICO!$D:$D,CONTROLE!O$1,NOTA_FISCAL_ANALITICO!$J:$J,CONTROLE!$A22) -> 0 | ... S22: =SUMIFS(NOTA_FISCAL_ANALITICO!$G:$G,NOTA_FISCAL_ANALITICO!$D:$D,CONTROLE!S$1,NOTA_FISCAL_ANALITICO!$J:$J,CONTROLE!$A22) -> 0
A23: INIBANK-1417 | B23: [Sustentação] Atendimento / Salesforce | C23: Realizado | G23: =SUM(H23:S23) -> 245176.79 | H23: =SUMIFS(NOTA_FISCAL_ANALITICO!$G:$G,NOTA_FISCAL_ANALITICO!$D:$D,CONTROLE!H$1,NOTA_FISCAL_ANALITICO!$J:$J,CONTROLE!$A23) -> 118699.28 | I23: =SUMIFS(NOTA_FISCAL_ANALITICO!$G:$G,NOTA_FISCAL_ANALITICO!$D:$D,CONTROLE!I$1,NOTA_FISCAL_ANALITICO!$J:$J,CONTROLE!$A23) -> 126477.51 | J23: =SUMIFS(NOTA_FISCAL_ANALITICO!$G:$G,NOTA_FISCAL_ANALITICO!$D:$D,CONTROLE!J$1,NOTA_FISCAL_ANALITICO!$J:$J,CONTROLE!$A23) -> 0 | K23: =SUMIFS(NOTA_FISCAL_ANALITICO!$G:$G,NOTA_FISCAL_ANALITICO!$D:$D,CONTROLE!K$1,NOTA_FISCAL_ANALITICO!$J:$J,CONTROLE!$A23) -> 0 | L23: =SUMIFS(NOTA_FISCAL_ANALITICO!$G:$G,NOTA_FISCAL_ANALITICO!$D:$D,CONTROLE!L$1,NOTA_FISCAL_ANALITICO!$J:$J,CONTROLE!$A23) -> 0 | M23: =SUMIFS(NOTA_FISCAL_ANALITICO!$G:$G,NOTA_FISCAL_ANALITICO!$D:$D,CONTROLE!M$1,NOTA_FISCAL_ANALITICO!$J:$J,CONTROLE!$A23) -> 0 | N23: =SUMIFS(NOTA_FISCAL_ANALITICO!$G:$G,NOTA_FISCAL_ANALITICO!$D:$D,CONTROLE!N$1,NOTA_FISCAL_ANALITICO!$J:$J,CONTROLE!$A23) -> 0 | O23: =SUMIFS(NOTA_FISCAL_ANALITICO!$G:$G,NOTA_FISCAL_ANALITICO!$D:$D,CONTROLE!O$1,NOTA_FISCAL_ANALITICO!$J:$J,CONTROLE!$A23) -> 0 | ... S23: =SUMIFS(NOTA_FISCAL_ANALITICO!$G:$G,NOTA_FISCAL_ANALITICO!$D:$D,CONTROLE!S$1,NOTA_FISCAL_ANALITICO!$J:$J,CONTROLE!$A23) -> 0
A24: INIBANK-1173 | B24: [Book] Squad Salesforce (Atendimento) | C24: Realizado | G24: =SUM(H24:S24) -> 451723.18 | H24: =SUMIFS(NOTA_FISCAL_ANALITICO!$G:$G,NOTA_FISCAL_ANALITICO!$D:$D,CONTROLE!H$1,NOTA_FISCAL_ANALITICO!$J:$J,CONTROLE!$A24) -> 155501.04 | I24: =SUMIFS(NOTA_FISCAL_ANALITICO!$G:$G,NOTA_FISCAL_ANALITICO!$D:$D,CONTROLE!I$1,NOTA_FISCAL_ANALITICO!$J:$J,CONTROLE!$A24) -> 296222.14 | J24: =SUMIFS(NOTA_FISCAL_ANALITICO!$G:$G,NOTA_FISCAL_ANALITICO!$D:$D,CONTROLE!J$1,NOTA_FISCAL_ANALITICO!$J:$J,CONTROLE!$A24) -> 0 | K24: =SUMIFS(NOTA_FISCAL_ANALITICO!$G:$G,NOTA_FISCAL_ANALITICO!$D:$D,CONTROLE!K$1,NOTA_FISCAL_ANALITICO!$J:$J,CONTROLE!$A24) -> 0 | L24: =SUMIFS(NOTA_FISCAL_ANALITICO!$G:$G,NOTA_FISCAL_ANALITICO!$D:$D,CONTROLE!L$1,NOTA_FISCAL_ANALITICO!$J:$J,CONTROLE!$A24) -> 0 | M24: =SUMIFS(NOTA_FISCAL_ANALITICO!$G:$G,NOTA_FISCAL_ANALITICO!$D:$D,CONTROLE!M$1,NOTA_FISCAL_ANALITICO!$J:$J,CONTROLE!$A24) -> 0 | N24: =SUMIFS(NOTA_FISCAL_ANALITICO!$G:$G,NOTA_FISCAL_ANALITICO!$D:$D,CONTROLE!N$1,NOTA_FISCAL_ANALITICO!$J:$J,CONTROLE!$A24) -> 0 | O24: =SUMIFS(NOTA_FISCAL_ANALITICO!$G:$G,NOTA_FISCAL_ANALITICO!$D:$D,CONTROLE!O$1,NOTA_FISCAL_ANALITICO!$J:$J,CONTROLE!$A24) -> 0 | ... S24: =SUMIFS(NOTA_FISCAL_ANALITICO!$G:$G,NOTA_FISCAL_ANALITICO!$D:$D,CONTROLE!S$1,NOTA_FISCAL_ANALITICO!$J:$J,CONTROLE!$A24) -> 0
A25: INIBANK-1349 | B25: Atendimento INVEST BANK | C25: Realizado | G25: =SUM(H25:S25) -> 56033.94 | H25: =SUMIFS(NOTA_FISCAL_ANALITICO!$G:$G,NOTA_FISCAL_ANALITICO!$D:$D,CONTROLE!H$1,NOTA_FISCAL_ANALITICO!$J:$J,CONTROLE!$A25) -> 56033.94 | I25: =SUMIFS(NOTA_FISCAL_ANALITICO!$G:$G,NOTA_FISCAL_ANALITICO!$D:$D,CONTROLE!I$1,NOTA_FISCAL_ANALITICO!$J:$J,CONTROLE!$A25) -> 0 | J25: =SUMIFS(NOTA_FISCAL_ANALITICO!$G:$G,NOTA_FISCAL_ANALITICO!$D:$D,CONTROLE!J$1,NOTA_FISCAL_ANALITICO!$J:$J,CONTROLE!$A25) -> 0 | K25: =SUMIFS(NOTA_FISCAL_ANALITICO!$G:$G,NOTA_FISCAL_ANALITICO!$D:$D,CONTROLE!K$1,NOTA_FISCAL_ANALITICO!$J:$J,CONTROLE!$A25) -> 0 | L25: =SUMIFS(NOTA_FISCAL_ANALITICO!$G:$G,NOTA_FISCAL_ANALITICO!$D:$D,CONTROLE!L$1,NOTA_FISCAL_ANALITICO!$J:$J,CONTROLE!$A25) -> 0 | M25: =SUMIFS(NOTA_FISCAL_ANALITICO!$G:$G,NOTA_FISCAL_ANALITICO!$D:$D,CONTROLE!M$1,NOTA_FISCAL_ANALITICO!$J:$J,CONTROLE!$A25) -> 0 | N25: =SUMIFS(NOTA_FISCAL_ANALITICO!$G:$G,NOTA_FISCAL_ANALITICO!$D:$D,CONTROLE!N$1,NOTA_FISCAL_ANALITICO!$J:$J,CONTROLE!$A25) -> 0 | O25: =SUMIFS(NOTA_FISCAL_ANALITICO!$G:$G,NOTA_FISCAL_ANALITICO!$D:$D,CONTROLE!O$1,NOTA_FISCAL_ANALITICO!$J:$J,CONTROLE!$A25) -> 0 | ... S25: =SUMIFS(NOTA_FISCAL_ANALITICO!$G:$G,NOTA_FISCAL_ANALITICO!$D:$D,CONTROLE!S$1,NOTA_FISCAL_ANALITICO!$J:$J,CONTROLE!$A25) -> 0
A27: INIBANK-611 | B27: Implantação do SalesForce para Central de Atendimento de Clientes PJ | C27: Resultado | G27: =SUM(H27:S27) -> -252716.37 | H27: =SUMIFS(H$2:H$26,$C$2:$C$26,"Forecast",$A$2:$A$26,$A27)-SUMIFS(H$2:H$26,$C$2:$C$26,"Realizado",$A$2:$A$26,$A27) -> -252716.37 | I27: =SUMIFS(I$2:I$26,$C$2:$C$26,"Forecast",$A$2:$A$26,$A27)-SUMIFS(I$2:I$26,$C$2:$C$26,"Realizado",$A$2:$A$26,$A27) -> 0 | J27: =SUMIFS(J$2:J$26,$C$2:$C$26,"Forecast",$A$2:$A$26,$A27)-SUMIFS(J$2:J$26,$C$2:$C$26,"Realizado",$A$2:$A$26,$A27) -> 0 | K27: =SUMIFS(K$2:K$26,$C$2:$C$26,"Forecast",$A$2:$A$26,$A27)-SUMIFS(K$2:K$26,$C$2:$C$26,"Realizado",$A$2:$A$26,$A27) -> 0 | L27: =SUMIFS(L$2:L$26,$C$2:$C$26,"Forecast",$A$2:$A$26,$A27)-SUMIFS(L$2:L$26,$C$2:$C$26,"Realizado",$A$2:$A$26,$A27) -> 0 | M27: =SUMIFS(M$2:M$26,$C$2:$C$26,"Forecast",$A$2:$A$26,$A27)-SUMIFS(M$2:M$26,$C$2:$C$26,"Realizado",$A$2:$A$26,$A27) -> 0 | N27: =SUMIFS(N$2:N$26,$C$2:$C$26,"Forecast",$A$2:$A$26,$A27)-SUMIFS(N$2:N$26,$C$2:$C$26,"Realizado",$A$2:$A$26,$A27) -> 0 | O27: =SUMIFS(O$2:O$26,$C$2:$C$26,"Forecast",$A$2:$A$26,$A27)-SUMIFS(O$2:O$26,$C$2:$C$26,"Realizado",$A$2:$A$26,$A27) -> 0 | ... S27: =SUMIFS(S$2:S$26,$C$2:$C$26,"Forecast",$A$2:$A$26,$A27)-SUMIFS(S$2:S$26,$C$2:$C$26,"Realizado",$A$2:$A$26,$A27) -> 0
A28: INIBANK-289 | B28: Sustentação Atendimento Salesforce Odin | C28: Resultado | G28: =SUM(H28:S28) -> 0 | H28: =SUMIFS(H$2:H$26,$C$2:$C$26,"Forecast",$A$2:$A$26,$A28)-SUMIFS(H$2:H$26,$C$2:$C$26,"Realizado",$A$2:$A$26,$A28) -> 0 | I28: =SUMIFS(I$2:I$26,$C$2:$C$26,"Forecast",$A$2:$A$26,$A28)-SUMIFS(I$2:I$26,$C$2:$C$26,"Realizado",$A$2:$A$26,$A28) -> 0 | J28: =SUMIFS(J$2:J$26,$C$2:$C$26,"Forecast",$A$2:$A$26,$A28)-SUMIFS(J$2:J$26,$C$2:$C$26,"Realizado",$A$2:$A$26,$A28) -> 0 | K28: =SUMIFS(K$2:K$26,$C$2:$C$26,"Forecast",$A$2:$A$26,$A28)-SUMIFS(K$2:K$26,$C$2:$C$26,"Realizado",$A$2:$A$26,$A28) -> 0 | L28: =SUMIFS(L$2:L$26,$C$2:$C$26,"Forecast",$A$2:$A$26,$A28)-SUMIFS(L$2:L$26,$C$2:$C$26,"Realizado",$A$2:$A$26,$A28) -> 0 | M28: =SUMIFS(M$2:M$26,$C$2:$C$26,"Forecast",$A$2:$A$26,$A28)-SUMIFS(M$2:M$26,$C$2:$C$26,"Realizado",$A$2:$A$26,$A28) -> 0 | N28: =SUMIFS(N$2:N$26,$C$2:$C$26,"Forecast",$A$2:$A$26,$A28)-SUMIFS(N$2:N$26,$C$2:$C$26,"Realizado",$A$2:$A$26,$A28) -> 0 | O28: =SUMIFS(O$2:O$26,$C$2:$C$26,"Forecast",$A$2:$A$26,$A28)-SUMIFS(O$2:O$26,$C$2:$C$26,"Realizado",$A$2:$A$26,$A28) -> 0 | ... S28: =SUMIFS(S$2:S$26,$C$2:$C$26,"Forecast",$A$2:$A$26,$A28)-SUMIFS(S$2:S$26,$C$2:$C$26,"Realizado",$A$2:$A$26,$A28) -> 0
A29: INIBANK-1417 | B29: [Sustentação] Atendimento / Salesforce | C29: Resultado | G29: =SUM(H29:S29) -> 1620541.2 | H29: =SUMIFS(H$2:H$26,$C$2:$C$26,"Forecast",$A$2:$A$26,$A29)-SUMIFS(H$2:H$26,$C$2:$C$26,"Realizado",$A$2:$A$26,$A29) -> 36777.22 | I29: =SUMIFS(I$2:I$26,$C$2:$C$26,"Forecast",$A$2:$A$26,$A29)-SUMIFS(I$2:I$26,$C$2:$C$26,"Realizado",$A$2:$A$26,$A29) -> 28998.99 | J29: =SUMIFS(J$2:J$26,$C$2:$C$26,"Forecast",$A$2:$A$26,$A29)-SUMIFS(J$2:J$26,$C$2:$C$26,"Realizado",$A$2:$A$26,$A29) -> 155476.5 | K29: =SUMIFS(K$2:K$26,$C$2:$C$26,"Forecast",$A$2:$A$26,$A29)-SUMIFS(K$2:K$26,$C$2:$C$26,"Realizado",$A$2:$A$26,$A29) -> 155476.5 | L29: =SUMIFS(L$2:L$26,$C$2:$C$26,"Forecast",$A$2:$A$26,$A29)-SUMIFS(L$2:L$26,$C$2:$C$26,"Realizado",$A$2:$A$26,$A29) -> 155476.5 | M29: =SUMIFS(M$2:M$26,$C$2:$C$26,"Forecast",$A$2:$A$26,$A29)-SUMIFS(M$2:M$26,$C$2:$C$26,"Realizado",$A$2:$A$26,$A29) -> 155476.5 | N29: =SUMIFS(N$2:N$26,$C$2:$C$26,"Forecast",$A$2:$A$26,$A29)-SUMIFS(N$2:N$26,$C$2:$C$26,"Realizado",$A$2:$A$26,$A29) -> 155476.5 | O29: =SUMIFS(O$2:O$26,$C$2:$C$26,"Forecast",$A$2:$A$26,$A29)-SUMIFS(O$2:O$26,$C$2:$C$26,"Realizado",$A$2:$A$26,$A29) -> 155476.5 | ... S29: =SUMIFS(S$2:S$26,$C$2:$C$26,"Forecast",$A$2:$A$26,$A29)-SUMIFS(S$2:S$26,$C$2:$C$26,"Realizado",$A$2:$A$26,$A29) -> 155476.5
A30: INIBANK-1173 | B30: [Book] Squad Salesforce (Atendimento) | C30: Resultado | G30: =SUM(H30:S30) -> 3503642.8 | H30: =SUMIFS(H$2:H$26,$C$2:$C$26,"Forecast",$A$2:$A$26,$A30)-SUMIFS(H$2:H$26,$C$2:$C$26,"Realizado",$A$2:$A$26,$A30) -> 174112.79 | I30: =SUMIFS(I$2:I$26,$C$2:$C$26,"Forecast",$A$2:$A$26,$A30)-SUMIFS(I$2:I$26,$C$2:$C$26,"Realizado",$A$2:$A$26,$A30) -> 33391.693 | J30: =SUMIFS(J$2:J$26,$C$2:$C$26,"Forecast",$A$2:$A$26,$A30)-SUMIFS(J$2:J$26,$C$2:$C$26,"Realizado",$A$2:$A$26,$A30) -> 329613.83 | K30: =SUMIFS(K$2:K$26,$C$2:$C$26,"Forecast",$A$2:$A$26,$A30)-SUMIFS(K$2:K$26,$C$2:$C$26,"Realizado",$A$2:$A$26,$A30) -> 329613.83 | L30: =SUMIFS(L$2:L$26,$C$2:$C$26,"Forecast",$A$2:$A$26,$A30)-SUMIFS(L$2:L$26,$C$2:$C$26,"Realizado",$A$2:$A$26,$A30) -> 329613.83 | M30: =SUMIFS(M$2:M$26,$C$2:$C$26,"Forecast",$A$2:$A$26,$A30)-SUMIFS(M$2:M$26,$C$2:$C$26,"Realizado",$A$2:$A$26,$A30) -> 329613.83 | N30: =SUMIFS(N$2:N$26,$C$2:$C$26,"Forecast",$A$2:$A$26,$A30)-SUMIFS(N$2:N$26,$C$2:$C$26,"Realizado",$A$2:$A$26,$A30) -> 329613.83 | O30: =SUMIFS(O$2:O$26,$C$2:$C$26,"Forecast",$A$2:$A$26,$A30)-SUMIFS(O$2:O$26,$C$2:$C$26,"Realizado",$A$2:$A$26,$A30) -> 329613.83 | ... S30: =SUMIFS(S$2:S$26,$C$2:$C$26,"Forecast",$A$2:$A$26,$A30)-SUMIFS(S$2:S$26,$C$2:$C$26,"Realizado",$A$2:$A$26,$A30) -> 329613.83
A31: INIBANK-1349 | B31: Atendimento INVEST BANK | C31: Resultado | G31: =SUM(H31:S31) -> 43966.06 | H31: =SUMIFS(H$2:H$26,$C$2:$C$26,"Forecast",$A$2:$A$26,$A31)-SUMIFS(H$2:H$26,$C$2:$C$26,"Realizado",$A$2:$A$26,$A31) -> 0 | I31: =SUMIFS(I$2:I$26,$C$2:$C$26,"Forecast",$A$2:$A$26,$A31)-SUMIFS(I$2:I$26,$C$2:$C$26,"Realizado",$A$2:$A$26,$A31) -> 0 | J31: =SUMIFS(J$2:J$26,$C$2:$C$26,"Forecast",$A$2:$A$26,$A31)-SUMIFS(J$2:J$26,$C$2:$C$26,"Realizado",$A$2:$A$26,$A31) -> 43966.06 | K31: =SUMIFS(K$2:K$26,$C$2:$C$26,"Forecast",$A$2:$A$26,$A31)-SUMIFS(K$2:K$26,$C$2:$C$26,"Realizado",$A$2:$A$26,$A31) -> 0 | L31: =SUMIFS(L$2:L$26,$C$2:$C$26,"Forecast",$A$2:$A$26,$A31)-SUMIFS(L$2:L$26,$C$2:$C$26,"Realizado",$A$2:$A$26,$A31) -> 0 | M31: =SUMIFS(M$2:M$26,$C$2:$C$26,"Forecast",$A$2:$A$26,$A31)-SUMIFS(M$2:M$26,$C$2:$C$26,"Realizado",$A$2:$A$26,$A31) -> 0 | N31: =SUMIFS(N$2:N$26,$C$2:$C$26,"Forecast",$A$2:$A$26,$A31)-SUMIFS(N$2:N$26,$C$2:$C$26,"Realizado",$A$2:$A$26,$A31) -> 0 | O31: =SUMIFS(O$2:O$26,$C$2:$C$26,"Forecast",$A$2:$A$26,$A31)-SUMIFS(O$2:O$26,$C$2:$C$26,"Realizado",$A$2:$A$26,$A31) -> 0 | ... S31: =SUMIFS(S$2:S$26,$C$2:$C$26,"Forecast",$A$2:$A$26,$A31)-SUMIFS(S$2:S$26,$C$2:$C$26,"Realizado",$A$2:$A$26,$A31) -> 0
A33: INIBANK-611 | B33: Implantação do SalesForce para Central de Atendimento de Clientes PJ | C33: Forecast Ajustado | G33: =G27 -> -252716.37 | H33: 0 | I33: 0 | J33: 0 | K33: 0 | L33: 0 | M33: 0 | N33: 0 | O33: 0 | P33: 0 | Q33: 0 | R33: 0 | S33: 0
A34: INIBANK-289 | B34: Sustentação Atendimento Salesforce Odin | C34: Forecast Ajustado | G34: =G28 -> 0 | H34: 0 | I34: 0 | J34: 0 | K34: 0 | L34: 0 | M34: 0 | N34: 0 | O34: 0 | P34: 0 | Q34: 0 | R34: 0 | S34: 0
A35: INIBANK-1417 | B35: [Sustentação] Atendimento / Salesforce | C35: Forecast Ajustado | G35: =G29 -> 1620541.2 | H35: 0 | I35: 0 | J35: =$G35/10 -> 162054.12 | K35: =$G35/10 -> 162054.12 | L35: =$G35/10 -> 162054.12 | M35: =$G35/10 -> 162054.12 | N35: =$G35/10 -> 162054.12 | O35: =$G35/10 -> 162054.12 | P35: =$G35/10 -> 162054.12 | Q35: =$G35/10 -> 162054.12 | ... S35: =$G35/10 -> 162054.12
A36: INIBANK-1173 | B36: [Book] Squad Salesforce (Atendimento) | C36: Forecast Ajustado | G36: =G30 -> 3503642.8 | H36: 0 | I36: 0 | J36: =$G36/10 -> 350364.28 | K36: =$G36/10 -> 350364.28 | L36: =$G36/10 -> 350364.28 | M36: =$G36/10 -> 350364.28 | N36: =$G36/10 -> 350364.28 | O36: =$G36/10 -> 350364.28 | P36: =$G36/10 -> 350364.28 | Q36: =$G36/10 -> 350364.28 | ... S36: =$G36/10 -> 350364.28
A37: INIBANK-1349 | B37: Atendimento INVEST BANK | C37: Forecast Ajustado | G37: =G31 -> 43966.06 | H37: 0 | I37: 0 | J37: =$G37/10 -> 4396.606 | K37: =$G37/10 -> 4396.606 | L37: =$G37/10 -> 4396.606 | M37: =$G37/10 -> 4396.606 | N37: =$G37/10 -> 4396.606 | O37: =$G37/10 -> 4396.606 | P37: =$G37/10 -> 4396.606 | Q37: =$G37/10 -> 4396.606 | ... S37: =$G37/10 -> 4396.606

Sheet FORNECEDOR
A1: CNPJ_PRESTADOR | B1: RAZAO_SOCIAL | C1: NOME_FANTASIA
A2: 65.599.953/0001-63 | B2: CAPGEMINI BRASIL LTDA | C2: Capgemini
A3: 00.607.819/0003-83 | B3: CWI SOFTWARE LTDA | C3: CWI
A4: 07.174.743/0001-27 | B4: GFT BRASIL CONSULTORIA INFORMÁTICA LTDA | C4: GFT Brasil
A5: 93.655.173/0006-33 | B5: META SERVICOS EM INFORMATICA S/A | C5: Meta
A6: 06.029.766/0004-28 | B6: OSF DIGITAL LTDA | C6: OSF Digital
A7: 24.231.517/0001-50 | B7: SYS4B INFORMATICA LTDA | C7: Sys4B

Sheet NOTA_FISCAL
A1: STATUS_NFE | B1: CNPJ_PRESTADOR | C1: RAZAO_SOCIAL | D1: NOME_FANTASIA | E1: CNPJ_TOMADOR | F1: COMPETENCIA | G1: NFE | H1: DATA_EMISSAO | I1: TOTAL_NFE | J1: APURACAO | K1: DATA_VENCIMENTO | L1: INICIATIVA | M1: INICIATIVA_DESCRICAO
A2: Autorizada | B2: 24.231.517/0001-50 | C2: SYS4B INFORMATICA LTDA | D2: Sys4B | E2: 61.198.164/0001-60 | F2: 45658 | G2: 2701 | H2: 45699 | I2: 191611.98 | J2: 22/12/24 a 21/01/25 | K2: 45759 | L2: INIBANK-54 | M2: Evoluções Salesforce para o Cartão
A3: Autorizada | B3: 24.231.517/0001-50 | C3: SYS4B INFORMATICA LTDA | D3: Sys4B | E3: 61.198.164/0001-60 | F3: 45658 | G3: 2702 | H3: 45699 | I3: 24607.42 | J3: 22/12/24 a 21/01/25 | K3: 45759 | L3: INIBANK-54 | M3: Evoluções Salesforce para o Cartão
A4: Autorizada | B4: 24.231.517/0001-50 | C4: SYS4B INFORMATICA LTDA | D4: Sys4B | E4: 61.198.164/0001-60 | F4: 45689 | G4: 2753 | H4: 45727 | I4: 303490.65 | J4: 22/01/25 a 21/02/25 | K4: 45787 | L4: INIBANK-54 | M4: Evoluções Salesforce para o Cartão
A5: Autorizada | B5: 24.231.517/0001-50 | C5: SYS4B INFORMATICA LTDA | D5: Sys4B | E5: 61.198.164/0001-60 | F5: 45717 | G5: 2791 | H5: 45749 | I5: 212597.4 | J5: 22/02/25 a 21/03/25 | K5: 45809 | L5: INIBANK-54 | M5: Evoluções Salesforce para o Cartão
A6: Autorizada | B6: 24.231.517/0001-50 | C6: SYS4B INFORMATICA LTDA | D6: Sys4B | E6: 61.198.164/0001-60 | F6: 45748 | G6: 2838 | H6: 45783 | I6: 284824.47 | J6: 22/03/25 a 21/04/25 | K6: 45843 | L6: INIBANK-54 | M6: Evoluções Salesforce para o Cartão
A7: Cancelada | B7: 24.231.517/0001-50 | C7: SYS4B INFORMATICA LTDA | D7: Sys4B | E7: 61.198.164/0001-60 | F7: 45778 | G7: 2886 | H7: 45811 | I7: 32224 | J7: 22/04/25 a 21/05/25 | K7: 45871 | L7: INIBANK-54 | M7: Evoluções Salesforce para o Cartão
A8: Autorizada | B8: 24.231.517/0001-50 | C8: SYS4B INFORMATICA LTDA | D8: Sys4B | E8: 61.198.164/0001-60 | F8: 45778 | G8: 2887 | H8: 45811 | I8: 283830.3 | J8: 22/04/25 a 21/05/25 | K8: 45871 | L8: INIBANK-54 | M8: Evoluções Salesforce para o Cartão
A9: Autorizada | B9: 65.599.953/0001-63 | C9: CAPGEMINI BRASIL LTDA | D9: Capgemini | E9: 04.862.600/0001-10 | F9: 45658 | G9: 145286 | H9: 45701 | I9: 131897.28 | J9: 01/01/25 a 31/01/25 | K9: 45746 | L9: INIBANK-611 | M9: Implantação do SalesForce para Central de Atendimento de Clientes PJ
A10: Autorizada | B10: 65.599.953/0001-63 | C10: CAPGEMINI BRASIL LTDA | D10: Capgemini | E10: 04.862.600/0001-10 | F10: 45689 | G10: 145885 | H10: 45729 | I10: 88245.42 | J10: 01/02/25 a 28/02/25 | K10: 45774 | L10: INIBANK-611 | M10: Implantação do SalesForce para Central de Atendimento de Clientes PJ
A11: Autorizada | B11: 65.599.953/0001-63 | C11: CAPGEMINI BRASIL LTDA | D11: Capgemini | E11: 61.198.164/0001-60 | F11: 45717 | I11: 146501.52 | J11: 01/03/25 a 31/03/25 | L11: INIBANK-226 | M11: Evoluções e Melhorias
A12: Autorizada | B12: 65.599.953/0001-63 | C12: CAPGEMINI BRASIL LTDA | D12: Capgemini | E12: 04.862.600/0001-10 | F12: 45717 | I12: 101456.94 | J12: 01/03/25 a 31/03/25 | L12: INIBANK-611 | M12: Implantação do SalesForce para Central de Atendimento de Clientes PJ
A13: Autorizada | B13: 65.599.953/0001-63 | C13: CAPGEMINI BRASIL LTDA | D13: Capgemini | E13: 61.198.164/0001-60 | F13: 45748 | G13: 147368 | H13: 45789 | I13: 89693.94 | J13: 01/04/25 a 21/04/25 | K13: 45834 | L13: INIBANK-226 | M13: Evoluções e Melhorias
A14: Autorizada | B14: 65.599.953/0001-63 | C14: CAPGEMINI BRASIL LTDA | D14: Capgemini | E14: 04.862.600/0001-10 | F14: 45748 | G14: 147373 | H14: 45789 | I14: 77929.2 | J14: 01/04/25 a 21/04/25 | K14: 45834 | L14: INIBANK-611 | M14: Implantação do SalesForce para Central de Atendimento de Clientes PJ
A15: Autorizada | B15: 65.599.953/0001-63 | C15: CAPGEMINI BRASIL LTDA | D15: Capgemini | E15: 04.862.600/0001-10 | F15: 45778 | G15: 148462 | H15: 45819 | I15: 121633.02 | J15: 22/04/25 a 21/05/25 | K15: 45864 | L15: INIBANK-611 | M15: Implantação do SalesForce para Central de Atendimento de Clientes PJ
A16: Autorizada | B16: 65.599.953/0001-63 | C16: CAPGEMINI BRASIL LTDA | D16: Capgemini | E16: 61.198.164/0001-60 | F16: 45778 | G16: 148457 | H16: 45819 | I16: 200222.04 | J16: 22/04/25 a 21/05/25 | K16: 45864 | L16: INIBANK-226 | M16: Evoluções e Melhorias
A17: Autorizada | B17: 06.029.766/0004-28 | C17: OSF DIGITAL LTDA | D17: OSF Digital | E17: 04.862.600/0001-10 | F17: 45717 | G17: 763 | H17: 45755 | I17: 41333.04 | J17: 01/03/25 a 31/03/25 | K17: 45785 | L17: INIBANK-611 | M17: Implantação do SalesForce para Central de Atendimento de Clientes PJ
A18: Autorizada | B18: 06.029.766/0004-28 | C18: OSF DIGITAL LTDA | D18: OSF Digital | E18: 04.862.600/0001-10 | F18: 45778 | G18: 883 | H18: 45818 | I18: 38556 | J18: 22/04/25 a 21/05/25 | K18: 45848 | L18: INIBANK-611 | M18: Implantação do SalesForce para Central de Atendimento de Clientes PJ
A19: Autorizada | B19: 06.029.766/0004-28 | C19: OSF DIGITAL LTDA | D19: OSF Digital | E19: 04.862.600/0001-10 | F19: 45778 | G19: 884 | H19: 45818 | I19: 54864.69 | J19: 22/04/25 a 21/05/25 | K19: 45848 | L19: INIBANK-611 | M19: Implantação do SalesForce para Central de Atendimento de Clientes PJ
A20: Autorizada | B20: 65.599.953/0001-63 | C20: CAPGEMINI BRASIL LTDA | D20: Capgemini | E20: 04.862.600/0001-10 | F20: 45809 | G20: 149204 | H20: 45846 | I20: 115880.7 | J20: 22/05/25 a 21/06/25 | K20: 45891 | L20: INIBANK-611 | M20: Implantação do SalesForce para Central de Atendimento de Clientes PJ
A21: Autorizada | B21: 65.599.953/0001-63 | C21: CAPGEMINI BRASIL LTDA | D21: Capgemini | E21: 61.198.164/0001-60 | F21: 45809 | G21: 149200 | H21: 45846 | I21: 104949.36 | J21: 22/05/25 a 21/06/25 | K21: 45891
A22: Autorizada | B22: 65.599.953/0001-63 | C22: CAPGEMINI BRASIL LTDA | D22: Capgemini | E22: 61.198.164/0001-60 | F22: 45809 | G22: 149207 | H22: 45846 | I22: 52130.88 | J22: 22/05/25 a 21/06/25 | K22: 45891
A23: Autorizada | B23: 06.029.766/0004-28 | C23: OSF DIGITAL LTDA | D23: OSF Digital | E23: 04.862.600/0001-10 | F23: 45809 | G23: 959 | H23: 45849 | I23: 38556 | J23: 22/05/25 a 21/06/25 | K23: 45880 | L23: INIBANK-611 | M23: Implantação do SalesForce para Central de Atendimento de Clientes PJ
A24: Autorizada | B24: 06.029.766/0004-28 | C24: OSF DIGITAL LTDA | D24: OSF Digital | E24: 04.862.600/0001-10 | F24: 45809 | G24: 960 | H24: 45849 | I24: 41333.04 | J24: 22/05/25 a 21/06/25 | K24: 45880 | L24: INIBANK-611 | M24: Implantação do SalesForce para Central de Atendimento de Clientes PJ
A25: Autorizada | B25: 24.231.517/0001-50 | C25: SYS4B INFORMATICA LTDA | D25: Sys4B | E25: 04.862.600/0001-10 | F25: 45809 | G25: 2937 | H25: 45845 | I25: 297661.94 | J25: 22/05/25 a 21/06/25 | K25: 45905 | L25: INIBANK-611 | M25: Implantação do SalesForce para Central de Atendimento de Clientes PJ
A26: Autorizada | B26: 24.231.517/0001-50 | C26: SYS4B INFORMATICA LTDA | D26: Sys4B | E26: 61.198.164/0001-60 | F26: 45809 | G26: 2947 | H26: 45848 | I26: 31754.33 | J26: 22/05/25 a 21/06/25 | K26: 45908 | L26: INIBANK-1173 | M26: [Book] Squad Salesforce (Atendimento)
A27: Cancelada | B27: 65.599.953/0001-63 | C27: CAPGEMINI BRASIL LTDA | D27: Capgemini | E27: 04.862.600/0001-10 | F27: 45839 | G27: 149983 | H27: 45874 | I27: 87082.32 | J27: 22/06/25 a 21/07/25 | K27: 45919 | L27: INIBANK-611 | M27: Implantação do SalesForce para Central de Atendimento de Clientes PJ
A28: Autorizada | B28: 65.599.953/0001-63 | C28: CAPGEMINI BRASIL LTDA | D28: Capgemini | E28: 04.862.600/0001-10 | F28: 45839 | G28: 149984 | H28: 45874 | I28: 114058.86 | J28: 22/06/25 a 21/07/25 | K28: 45919 | L28: INIBANK-611 | M28: Implantação do SalesForce para Central de Atendimento de Clientes PJ
A29: Cancelada | B29: 65.599.953/0001-63 | C29: CAPGEMINI BRASIL LTDA | D29: Capgemini | E29: 61.198.164/0001-60 | F29: 45839 | G29: 149989 | H29: 45874 | I29: 46181.16 | J29: 22/06/25 a 21/07/25 | K29: 45919 | L29: INIBANK-1173 | M29: [Book] Squad Salesforce (Atendimento)
A30: Cancelada | B30: 06.029.766/0004-28 | C30: OSF DIGITAL LTDA | D30: OSF Digital | E30: 04.862.600/0001-10 | F30: 45839 | G30: 1023 | H30: 45876 | I30: 25704 | J30: 22/06/25 a 21/07/25 | K30: 45908 | L30: INIBANK-611 | M30: Implantação do SalesForce para Central de Atendimento de Clientes PJ
A31: Autorizada | B31: 24.231.517/0001-50 | C31: SYS4B INFORMATICA LTDA | D31: Sys4B | E31: 61.198.164/0001-60 | F31: 45839 | G31: 2978 | H31: 45874 | I31: 32224 | J31: 22/06/25 a 21/07/25 | K31: 45934 | L31: INIBANK-1173 | M31: [Book] Squad Salesforce (Atendimento)
A32: Cancelada | B32: 06.029.766/0004-28 | C32: OSF DIGITAL LTDA | D32: OSF Digital | E32: 04.862.600/0001-10 | F32: 45839 | G32: 1024 | H32: 45876 | I32: 11809.44 | J32: 22/06/25 a 21/07/25 | K32: 45908 | L32: INIBANK-611 | M32: Implantação do SalesForce para Central de Atendimento de Clientes PJ
A33: Cancelada | B33: 24.231.517/0001-50 | C33: SYS4B INFORMATICA LTDA | D33: Sys4B | E33: 61.198.164/0001-60 | F33: 45839 | G33: 2977 | H33: 45874 | I33: 276726.81 | J33: 22/06/25 a 21/07/25 | K33: 45934 | L33: INIBANK-1173 | M33: [Book] Squad Salesforce (Atendimento)
A34: Autorizada | B34: 06.029.766/0004-28 | C34: OSF DIGITAL LTDA | D34: OSF Digital | E34: 04.862.600/0001-10 | F34: 45839 | G34: 1043 | H34: 45883 | I34: 37513.44 | J34: 22/06/25 a 21/07/25 | K34: 45908 | L34: INIBANK-611 | M34: Implantação do SalesForce para Central de Atendimento de Clientes PJ
... A137: Autorizada | B137: 24.231.517/0001-50 | C137: SYS4B INFORMATICA LTDA | D137: Sys4B | E137: 61.198.164/0001-60 | F137: 46054 | G137: 3297 | H137: 46085 | I137: 126477.51 | J137: 22/01/25 a 21/02/26 | K137: 46131 | L137: INIBANK-1417 | M137: [Sustentação] Atendimento / Salesforce

Sheet NOTA_FISCAL_ANALITICO
A1: CNPJ_PRESTADOR | B1: RAZAO_SOCIAL | C1: NOME_FANTASIA | D1: COMPETENCIA | E1: NFE | F1: DATA_EMISSAO | G1: SUBTOTAL_NFE | H1: APURACAO | I1: DATA_VENCIMENTO | J1: INICIATIVA | K1: MATRICULA | L1: NOME_PROFISSIONAL | M1: PAPEL_PRESTADOR | N1: TOTAL_HORAS | O1: HH
A2: 24.231.517/0001-50 | B2: SYS4B INFORMATICA LTDA | C2: Sys4B | D2: 45658 | E2: 2701 | F2: 45699 | G2: 191611.98 | H2: 22/12/24 a 21/01/25 | I2: 45759 | J2: INIBANK-54 | L2: - | N2: 0 | O2: 0
A3: 24.231.517/0001-50 | B3: SYS4B INFORMATICA LTDA | C3: Sys4B | D3: 45658 | E3: 2702 | F3: 45699 | G3: 24607.42 | H3: 22/12/24 a 21/01/25 | I3: 45759 | J3: INIBANK-54 | L3: - | N3: 0 | O3: 0
A4: 65.599.953/0001-63 | B4: CAPGEMINI BRASIL LTDA | C4: Capgemini | D4: 45658 | E4: 145286 | F4: 45701 | G4: 65948.64 | H4: 22/12/24 a 21/01/25 | I4: 45746 | J4: INIBANK-611 | L4: - | N4: 0 | O4: 0
A5: 65.599.953/0001-63 | B5: CAPGEMINI BRASIL LTDA | C5: Capgemini | D5: 45658 | E5: 145286 | F5: 45701 | G5: 65948.64 | H5: 22/12/24 a 21/01/25 | I5: 45746 | J5: INIBANK-226 | L5: - | N5: 0 | O5: 0
A6: 24.231.517/0001-50 | B6: SYS4B INFORMATICA LTDA | C6: Sys4B | D6: 45689 | E6: 2753 | F6: 45727 | G6: 151745.33 | H6: 22/01/25 a 21/02/25 | I6: 45787 | J6: INIBANK-54 | L6: - | N6: 0 | O6: 0
A7: 24.231.517/0001-50 | B7: SYS4B INFORMATICA LTDA | C7: Sys4B | D7: 45689 | E7: 2753 | F7: 45727 | G7: 151745.33 | H7: 22/01/25 a 21/02/25 | I7: 45787 | J7: INIBANK-225 | L7: - | N7: 0 | O7: 0
A8: 65.599.953/0001-63 | B8: CAPGEMINI BRASIL LTDA | C8: Capgemini | D8: 45689 | E8: 145885 | F8: 45729 | G8: 9928.38 | H8: 22/01/25 a 21/02/25 | I8: 45774 | J8: INIBANK-611 | L8: SAMUEL PEREIRA JUNIOR | M8: Desenvolvedor Salesforce Sênior | N8: 49 | O8: 202.62
A9: 65.599.953/0001-63 | B9: CAPGEMINI BRASIL LTDA | C9: Capgemini | D9: 45689 | E9: 145885 | F9: 45729 | G9: 32419.2 | H9: 22/01/25 a 21/02/25 | I9: 45774 | J9: INIBANK-611 | K9: P0661715 | L9: MARCEL VALLIM MOREIRA | M9: Desenvolvedor Salesforce Sênior | N9: 160 | O9: 202.62
A10: 65.599.953/0001-63 | B10: CAPGEMINI BRASIL LTDA | C10: Capgemini | D10: 45689 | E10: 145885 | F10: 45729 | G10: 45897.84 | H10: 22/01/25 a 21/02/25 | I10: 45774 | J10: INIBANK-611 | K10: P0661361 | L10: FERNANDO DA SILVA TREVISAN | M10: Tech Lead Salesforce | N10: 162 | O10: 283.32
A11: 24.231.517/0001-50 | B11: SYS4B INFORMATICA LTDA | C11: Sys4B | D11: 45717 | E11: 2791 | F11: 45749 | G11: 17161.46 | H11: 22/02/25 a 21/03/25 | I11: 45809 | J11: INIBANK-54 | K11: P0650648 | L11: Lucas Takita | M11: Desenvolvedor Salesforce Sênior | N11: 82.25 | O11: 208.65
A12: 24.231.517/0001-50 | B12: SYS4B INFORMATICA LTDA | C12: Sys4B | D12: 45717 | E12: 2791 | F12: 45749 | G12: 15022.8 | H12: 22/02/25 a 21/03/25 | I12: 45809 | J12: INIBANK-54 | K12: P0651731 | L12: Fernando Piovezan | M12: Desenvolvedor Salesforce Sênior | N12: 72 | O12: 208.65
A13: 24.231.517/0001-50 | B13: SYS4B INFORMATICA LTDA | C13: Sys4B | D13: 45717 | E13: 2791 | F13: 45749 | G13: 14188.2 | H13: 22/02/25 a 21/03/25 | I13: 45809 | J13: INIBANK-54 | K13: P0661870 | L13: Gustavo Siqueira Martins | M13: Desenvolvedor Salesforce Sênior | N13: 68 | O13: 208.65
A14: 24.231.517/0001-50 | B14: SYS4B INFORMATICA LTDA | C14: Sys4B | D14: 45717 | E14: 2791 | F14: 45749 | G14: 14605.5 | H14: 22/02/25 a 21/03/25 | I14: 45809 | J14: INIBANK-54 | K14: P0654694 | L14: Carlos Eduardo Santos Santana | M14: Desenvolvedor Salesforce Sênior | N14: 70 | O14: 208.65
A15: 24.231.517/0001-50 | B15: SYS4B INFORMATICA LTDA | C15: Sys4B | D15: 45717 | E15: 2791 | F15: 45749 | G15: 16223.25 | H15: 22/02/25 a 21/03/25 | I15: 45809 | J15: INIBANK-54 | K15: P0660057 | L15: Cleiton Lima de Jesus | M15: Desenvolvedor Salesforce Sênior | N15: 72.75 | O15: 223
A16: 24.231.517/0001-50 | B16: SYS4B INFORMATICA LTDA | C16: Sys4B | D16: 45717 | E16: 2791 | F16: 45749 | G16: 15610 | H16: 22/02/25 a 21/03/25 | I16: 45809 | J16: INIBANK-54 | K16: P0656797 | L16: Gustavo Seiji Onizuka | M16: Desenvolvedor Salesforce | N16: 70 | O16: 223
A17: 24.231.517/0001-50 | B17: SYS4B INFORMATICA LTDA | C17: Sys4B | D17: 45717 | E17: 2791 | F17: 45749 | G17: 15283.61 | H17: 22/02/25 a 21/03/25 | I17: 45809 | J17: INIBANK-54 | K17: P0662312 | L17: Francielle Thiezo Revesso Pinto | M17: Administrador Salesforce | N17: 73.25 | O17: 208.65
A18: 24.231.517/0001-50 | B18: SYS4B INFORMATICA LTDA | C18: Sys4B | D18: 45717 | E18: 2791 | F18: 45749 | G18: 14709.83 | H18: 22/02/25 a 21/03/25 | I18: 45809 | J18: INIBANK-54 | K18: P0658519 | L18: Leonardo Lins | M18: Desenvolvedor Salesforce Sênior | N18: 70.5 | O18: 208.65
A19: 24.231.517/0001-50 | B19: SYS4B INFORMATICA LTDA | C19: Sys4B | D19: 45717 | E19: 2791 | F19: 45749 | G19: 3110 | H19: 22/02/25 a 21/03/25 | I19: 45809 | J19: INIBANK-54 | K19: P0000000 | L19: Plantão Salesforce Odin | M19: Desenvolvedor Salesforce Sênior | N19: 0 | O19: 0
A20: 24.231.517/0001-50 | B20: SYS4B INFORMATICA LTDA | C20: Sys4B | D20: 45717 | E20: 2791 | F20: 45749 | G20: -19615.95 | H20: 22/02/25 a 21/03/25 | I20: 45809 | J20: INIBANK-54 | L20: Desconto 3/3 | N20: 0 | O20: 0
A21: 24.231.517/0001-50 | B21: SYS4B INFORMATICA LTDA | C21: Sys4B | D21: 45717 | E21: 2791 | F21: 45749 | G21: 17161.46 | H21: 22/02/25 a 21/03/25 | I21: 45809 | J21: INIBANK-225 | K21: P0650648 | L21: Lucas Takita | M21: Desenvolvedor Salesforce Sênior | N21: 82.25 | O21: 208.65
A22: 24.231.517/0001-50 | B22: SYS4B INFORMATICA LTDA | C22: Sys4B | D22: 45717 | E22: 2791 | F22: 45749 | G22: 15022.8 | H22: 22/02/25 a 21/03/25 | I22: 45809 | J22: INIBANK-225 | K22: P0651731 | L22: Fernando Piovezan | M22: Desenvolvedor Salesforce Sênior | N22: 72 | O22: 208.65
A23: 24.231.517/0001-50 | B23: SYS4B INFORMATICA LTDA | C23: Sys4B | D23: 45717 | E23: 2791 | F23: 45749 | G23: 14188.2 | H23: 22/02/25 a 21/03/25 | I23: 45809 | J23: INIBANK-225 | K23: P0661870 | L23: Gustavo Siqueira Martins | M23: Desenvolvedor Salesforce Sênior | N23: 68 | O23: 208.65
A24: 24.231.517/0001-50 | B24: SYS4B INFORMATICA LTDA | C24: Sys4B | D24: 45717 | E24: 2791 | F24: 45749 | G24: 14605.5 | H24: 22/02/25 a 21/03/25 | I24: 45809 | J24: INIBANK-225 | K24: P0654694 | L24: Carlos Eduardo Santos Santana | M24: Desenvolvedor Salesforce Sênior | N24: 70 | O24: 208.65
A25: 24.231.517/0001-50 | B25: SYS4B INFORMATICA LTDA | C25: Sys4B | D25: 45717 | E25: 2791 | F25: 45749 | G25: 16223.25 | H25: 22/02/25 a 21/03/25 | I25: 45809 | J25: INIBANK-225 | K25: P0660057 | L25: Cleiton Lima de Jesus | M25: Desenvolvedor Salesforce Sênior | N25: 72.75 | O25: 223
A26: 24.231.517/0001-50 | B26: SYS4B INFORMATICA LTDA | C26: Sys4B | D26: 45717 | E26: 2791 | F26: 45749 | G26: 15610 | H26: 22/02/25 a 21/03/25 | I26: 45809 | J26: INIBANK-225 | K26: P0656797 | L26: Gustavo Seiji Onizuka | M26: Desenvolvedor Salesforce | N26: 70 | O26: 223
A27: 24.231.517/0001-50 | B27: SYS4B INFORMATICA LTDA | C27: Sys4B | D27: 45717 | E27: 2791 | F27: 45749 | G27: 15283.61 | H27: 22/02/25 a 21/03/25 | I27: 45809 | J27: INIBANK-225 | K27: P0662312 | L27: Francielle Thiezo Revesso Pinto | M27: Administrador Salesforce | N27: 73.25 | O27: 208.65
A28: 24.231.517/0001-50 | B28: SYS4B INFORMATICA LTDA | C28: Sys4B | D28: 45717 | E28: 2791 | F28: 45749 | G28: 14709.83 | H28: 22/02/25 a 21/03/25 | I28: 45809 | J28: INIBANK-225 | K28: P0658519 | L28: Leonardo Lins | M28: Desenvolvedor Salesforce Sênior | N28: 70.5 | O28: 208.65
A29: 24.231.517/0001-50 | B29: SYS4B INFORMATICA LTDA | C29: Sys4B | D29: 45717 | E29: 2791 | F29: 45749 | G29: 3110 | H29: 22/02/25 a 21/03/25 | I29: 45809 | J29: INIBANK-225 | K29: P0000000 | L29: Plantão Salesforce Odin | M29: Desenvolvedor Salesforce Sênior | N29: 0 | O29: 0
A30: 24.231.517/0001-50 | B30: SYS4B INFORMATICA LTDA | C30: Sys4B | D30: 45717 | E30: 2791 | F30: 45749 | G30: -19615.95 | H30: 22/02/25 a 21/03/25 | I30: 45809 | J30: INIBANK-225 | L30: Desconto 3/3 | N30: 0 | O30: 0
A31: 65.599.953/0001-63 | B31: CAPGEMINI BRASIL LTDA | C31: Capgemini | D31: 45717 | G31: 21815.64 | H31: 22/02/25 a 21/03/25 | J31: INIBANK-226 | K31: P0659788 | L31: RAPHAEL ROSA DE BARROS | M31: Tech Lead Salesforce | N31: 77 | O31: 283.32
A32: 65.599.953/0001-63 | B32: CAPGEMINI BRASIL LTDA | C32: Capgemini | D32: 45717 | G32: 11332.8 | H32: 22/02/25 a 21/03/25 | J32: INIBANK-226 | K32: P0659789 | L32: GUSTAVO COSTA TENORIO | M32: Arquiteto Especialista Salesforce | N32: 40 | O32: 283.32
A33: 65.599.953/0001-63 | B33: CAPGEMINI BRASIL LTDA | C33: Capgemini | D33: 45717 | G33: 42252.96 | H33: 22/02/25 a 21/03/25 | J33: INIBANK-226 | K33: P0659891 | L33: MARIIA NIKONOVA | M33: Desenvolvedor Salesforce Sênior | N33: 164 | O33: 257.64
A34: 65.599.953/0001-63 | B34: CAPGEMINI BRASIL LTDA | C34: Capgemini | D34: 45717 | G34: 40707.12 | H34: 22/02/25 a 21/03/25 | J34: INIBANK-226 | K34: P0659884 | L34: VICTOR BERNARDES ARAUJO | M34: Desenvolvedor Salesforce Sênior | N34: 158 | O34: 257.64
A35: 65.599.953/0001-63 | B35: CAPGEMINI BRASIL LTDA | C35: Capgemini | D35: 45717 | G35: 30393 | H35: 22/02/25 a 21/03/25 | J35: INIBANK-226 | K35: P0654808 | L35: Nivaldo Estevao da Silva Junior | M35: Desenvolvedor Pleno | N35: 150 | O35: 202.62
A36: 65.599.953/0001-63 | B36: CAPGEMINI BRASIL LTDA | C36: Capgemini | D36: 45717 | G36: 13778.16 | H36: 22/02/25 a 21/03/25 | J36: INIBANK-611 | L36: SAMUEL PEREIRA JUNIOR | M36: Desenvolvedor Salesforce Sênior | N36: 68 | O36: 202.62
A37: 65.599.953/0001-63 | B37: CAPGEMINI BRASIL LTDA | C37: Capgemini | D37: 45717 | G37: 9725.76 | H37: 22/02/25 a 21/03/25 | J37: INIBANK-611 | K37: P0663000 | L37: DIEGO FELIPE SOUZA OLIVEIRA | M37: Desenvolvedor Salesforce Sênior | N37: 48 | O37: 202.62
A38: 65.599.953/0001-63 | B38: CAPGEMINI BRASIL LTDA | C38: Capgemini | D38: 45717 | G38: 32621.82 | H38: 22/02/25 a 21/03/25 | J38: INIBANK-611 | K38: P0661715 | L38: MARCEL VALLIM MOREIRA | M38: Desenvolvedor Salesforce Sênior | N38: 161 | O38: 202.62
A39: 65.599.953/0001-63 | B39: CAPGEMINI BRASIL LTDA | C39: Capgemini | D39: 45717 | G39: 45331.2 | H39: 22/02/25 a 21/03/25 | J39: INIBANK-611 | K39: P0661361 | L39: FERNANDO DA SILVA TREVISAN | M39: Tech Lead Salesforce | N39: 160 | O39: 283.32
A40: 06.029.766/0004-28 | B40: OSF DIGITAL LTDA | C40: OSF Digital | D40: 45717 | E40: 763 | F40: 45755 | G40: 41333.04 | H40: 22/02/25 a 21/03/25 | I40: 45785 | J40: INIBANK-611 | K40: P0660856 | L40: Paulo Henrique Alves Pereira | M40: Desenvolvedor Salesforce Junior | N40: 168 | O40: 246.03
A41: 24.231.517/0001-50 | B41: SYS4B INFORMATICA LTDA | C41: Sys4B | D41: 45748 | E41: 2838 | F41: 45783 | G41: 19508.78 | H41: 22/03/25 a 21/04/25 | I41: 45843 | J41: INIBANK-54 | K41: P0650648 | L41: Lucas Takita | M41: Desenvolvedor Salesforce Sênior | N41: 93.5 | O41: 208.65
A42: 24.231.517/0001-50 | B42: SYS4B INFORMATICA LTDA | C42: Sys4B | D42: 45748 | E42: 2838 | F42: 45783 | G42: 15857.4 | H42: 22/03/25 a 21/04/25 | I42: 45843 | J42: INIBANK-54 | K42: P0651731 | L42: Fernando Piovezan | M42: Desenvolvedor Salesforce Sênior | N42: 76 | O42: 208.65
A43: 24.231.517/0001-50 | B43: SYS4B INFORMATICA LTDA | C43: Sys4B | D43: 45748 | E43: 2838 | F43: 45783 | G43: 8346 | H43: 22/03/25 a 21/04/25 | I43: 45843 | J43: INIBANK-54 | K43: P0661870 | L43: Gustavo Siqueira Martins | M43: Desenvolvedor Salesforce Sênior | N43: 40 | O43: 208.65
A44: 24.231.517/0001-50 | B44: SYS4B INFORMATICA LTDA | C44: Sys4B | D44: 45748 | E44: 2838 | F44: 45783 | G44: 17474.44 | H44: 22/03/25 a 21/04/25 | I44: 45843 | J44: INIBANK-54 | K44: P0654694 | L44: Carlos Eduardo Santos Santana | M44: Desenvolvedor Salesforce Sênior | N44: 83.75 | O44: 208.65
A45: 24.231.517/0001-50 | B45: SYS4B INFORMATICA LTDA | C45: Sys4B | D45: 45748 | E45: 2838 | F45: 45783 | G45: 17617 | H45: 22/03/25 a 21/04/25 | I45: 45843 | J45: INIBANK-54 | K45: P0660057 | L45: Cleiton Lima de Jesus | M45: Desenvolvedor Salesforce Sênior | N45: 79 | O45: 223
A46: 24.231.517/0001-50 | B46: SYS4B INFORMATICA LTDA | C46: Sys4B | D46: 45748 | E46: 2838 | F46: 45783 | G46: 16948 | H46: 22/03/25 a 21/04/25 | I46: 45843 | J46: INIBANK-54 | K46: P0656797 | L46: Gustavo Seiji Onizuka | M46: Desenvolvedor Salesforce | N46: 76 | O46: 223
A47: 24.231.517/0001-50 | B47: SYS4B INFORMATICA LTDA | C47: Sys4B | D47: 45748 | E47: 2838 | F47: 45783 | G47: 17474.44 | H47: 22/03/25 a 21/04/25 | I47: 45843 | J47: INIBANK-54 | K47: P0662312 | L47: Francielle Thiezo Revesso Pinto | M47: Administrador Salesforce | N47: 83.75 | O47: 208.65
A48: 24.231.517/0001-50 | B48: SYS4B INFORMATICA LTDA | C48: Sys4B | D48: 45748 | E48: 2838 | F48: 45783 | G48: 15857.4 | H48: 22/03/25 a 21/04/25 | I48: 45843 | J48: INIBANK-54 | K48: P0658519 | L48: Leonardo Lins | M48: Desenvolvedor Salesforce Sênior | N48: 76 | O48: 208.65
A49: 24.231.517/0001-50 | B49: SYS4B INFORMATICA LTDA | C49: Sys4B | D49: 45748 | E49: 2838 | F49: 45783 | G49: 13328.79 | H49: 22/03/25 a 21/04/25 | I49: 45843 | J49: INIBANK-54 | K49: P0000000 | L49: Plantão Salesforce Odin | M49: Desenvolvedor Salesforce Sênior | N49: 0 | O49: 0
A50: 24.231.517/0001-50 | B50: SYS4B INFORMATICA LTDA | C50: Sys4B | D50: 45748 | E50: 2838 | F50: 45783 | G50: 19508.78 | H50: 22/03/25 a 21/04/25 | I50: 45843 | J50: INIBANK-225 | K50: P0650648 | L50: Lucas Takita | M50: Desenvolvedor Salesforce Sênior | N50: 93.5 | O50: 208.65
A51: 24.231.517/0001-50 | B51: SYS4B INFORMATICA LTDA | C51: Sys4B | D51: 45748 | E51: 2838 | F51: 45783 | G51: 15857.4 | H51: 22/03/25 a 21/04/25 | I51: 45843 | J51: INIBANK-225 | K51: P0651731 | L51: Fernando Piovezan | M51: Desenvolvedor Salesforce Sênior | N51: 76 | O51: 208.65
... A210: 07.174.743/0001-27 | B210: GFT BRASIL CONSULTORIA INFORMÁTICA LTDA | C210: GFT Brasil | D210: 45931 | E210: 43904 | F210: 45967 | G210: 32334.72 | H210: 22/09/25 a 21/10/25 | I210: 45997 | J210: INIBANK-611 | K210: P0659934 | L210: Jorge Cardoso Filho | M210: Analista de Teste | N210: 204.75 | O210: 184.6
A211: 93.655.173/0006-33 | B211: META SERVICOS EM INFORMATICA S/A | C211: Meta | D211: 45931 | E211: 15795 | F211: 45966 | G211: 35190.96 | H211: 22/09/25 a 21/10/25 | J211: INIBANK-1173 | K211: P0661166 | L211: Adejailson Antonio De Luna | M211: Product Owner | N211: 182.45 | O211: 192.88
A212: 93.655.173/0006-33 | B212: META SERVICOS EM INFORMATICA S/A | C212: Meta | D212: 45962 | E212: 15895 | F212: 45993 | G212: 35846.75 | H212: 22/09/25 a 21/10/25 | I212: 46023 | J212: INIBANK-1173 | K212: P0661166 | L212: Adejailson Antonio De Luna | M212: Product Owner | N212: 185.85 | O212: 192.88
A213: 24.231.517/0001-50 | B213: SYS4B INFORMATICA LTDA | C213: Sys4B | D213: 45962 | E213: 3227 | F213: 46027 | G213: 15077.84 | H213: 22/09/25 a 21/10/25 | I213: 46073 | J213: INIBANK-289 | K213: P0650648 | L213: Lucas Takita | M213: Desenvolvedor Salesforce Sênior | N213: 181.5 | O213: 213.87
A214: 24.231.517/0001-50 | B214: SYS4B INFORMATICA LTDA | C214: Sys4B | D214: 45962 | E214: 3227 | F214: 46027 | G214: 34636.16 | H214: 22/09/25 a 21/10/25 | I214: 46073 | J214: INIBANK-289 | K214: P0663654 | L214: Gabriel Costa Datovo Inoue Maekawa | M214: Desenvolvedor Pleno | N214: 96 | O214: 191.36
A215: 24.231.517/0001-50 | B215: SYS4B INFORMATICA LTDA | C215: Sys4B | D215: 45962 | E215: 3227 | F215: 46027 | G215: 40207.56 | H215: 22/09/25 a 21/10/25 | I215: 46073 | J215: INIBANK-289 | K215: P0662312 | L215: Francielle Thiezo Revesso Pinto | M215: Administrador Salesforce | N215: 178 | O215: 213.87
A216: 24.231.517/0001-50 | B216: SYS4B INFORMATICA LTDA | C216: Sys4B | D216: 45962 | E216: 3227 | F216: 46027 | G216: 28744.13 | H216: 22/09/25 a 21/10/25 | I216: 46073 | J216: INIBANK-289 | K216: P0000000 | L216: Plantão Salesforce Odin | M216: Desenvolvedor Salesforce Sênior | N216: 0 | O216: 0
A217: 24.231.517/0001-50 | B217: SYS4B INFORMATICA LTDA | C217: Sys4B | D217: 45992 | E217: 3238 | F217: 46028 | G217: 34540.01 | H217: 22/11/25 a 21/12/25 | I217: 46074 | J217: INIBANK-289 | K217: P0650648 | L217: Lucas Takita | M217: Desenvolvedor Salesforce Sênior | N217: 161.5 | O217: 213.87
A218: 24.231.517/0001-50 | B218: SYS4B INFORMATICA LTDA | C218: Sys4B | D218: 45992 | E218: 3238 | F218: 46028 | G218: 23920 | H218: 22/11/25 a 21/12/25 | I218: 46074 | J218: INIBANK-289 | K218: P0663654 | L218: Gabriel Costa Datovo Inoue Maekawa | M218: Desenvolvedor Pleno | N218: 125 | O218: 191.36
A219: 24.231.517/0001-50 | B219: SYS4B INFORMATICA LTDA | C219: Sys4B | D219: 45992 | E219: 3238 | F219: 46028 | G219: 35930.16 | H219: 22/11/25 a 21/12/25 | I219: 46074 | J219: INIBANK-289 | K219: P0662312 | L219: Francielle Thiezo Revesso Pinto | M219: Administrador Salesforce | N219: 168 | O219: 213.87
A220: 24.231.517/0001-50 | B220: SYS4B INFORMATICA LTDA | C220: Sys4B | D220: 45992 | E220: 3238 | F220: 46028 | G220: 28744.13 | H220: 22/11/25 a 21/12/25 | I220: 46074 | J220: INIBANK-289 | K220: P0000000 | L220: Plantão Salesforce Odin | M220: Desenvolvedor Salesforce Sênior | N220: 0 | O220: 0
A221: 24.231.517/0001-50 | B221: SYS4B INFORMATICA LTDA | C221: Sys4B | D221: 45992 | E221: 3239 | F221: 46029 | G221: 9143.2 | H221: 22/11/25 a 21/12/25 | I221: 46075 | J221: INIBANK-1173 | K221: P0660057 | L221: Cleiton Lima de Jesus | M221: Desenvolvedor Salesforce Sênior | N221: 40 | O221: 228.58
A222: 24.231.517/0001-50 | B222: SYS4B INFORMATICA LTDA | C222: Sys4B | D222: 45992 | E222: 3239 | F222: 46029 | G222: 32248 | H222: 22/11/25 a 21/12/25 | I222: 46075 | J222: INIBANK-1173 | K222: P0662282 | L222: Joyce Andrade | M222: Consultor UX/UI | N222: 160 | O222: 201.55
A223: 24.231.517/0001-50 | B223: SYS4B INFORMATICA LTDA | C223: Sys4B | D223: 45992 | E223: 3239 | F223: 46029 | G223: 32508.24 | H223: 22/11/25 a 21/12/25 | I223: 46075 | J223: INIBANK-1173 | K223: P0656797 | L223: Gustavo Seiji Onizuka | M223: Desenvolvedor Salesforce | N223: 152 | O223: 213.87
... A259: 07.174.743/0001-27 | B259: GFT BRASIL CONSULTORIA INFORMÁTICA LTDA | C259: GFT Brasil | D259: 45992 | E259: 46398 | F259: 46038 | G259: 30218.4 | H259: 22/11/25 a 21/12/25 | I259: 46068 | J259: INIBANK-611 | K259: P0659934 | L259: Jorge Cardoso Filho | M259: Analista de Teste | N259: 204.75 | O259: 184.6
A260: 93.655.173/0006-33 | B260: META SERVICOS EM INFORMATICA S/A | C260: Meta | D260: 45992 | G260: 35846.75 | H260: 22/11/25 a 21/12/25 | J260: INIBANK-1173 | K260: P0661166 | L260: Adejailson Antonio De Luna | M260: Product Owner | N260: 185.85 | O260: 192.88
A261: 65.599.953/0001-63 | B261: CAPGEMINI BRASIL LTDA | C261: Capgemini | D261: 46023 | E261: 155805 | F261: 46055 | G261: 32699.44 | H261: 22/12/25 a 21/01/26 | I261: 46115 | J261: INIBANK-1173 | K261: P0661738 | L261: Erick Delfino Silva | M261: Analista de Teste Sênior | N261: 168.78 | O261: 193.74
A262: 65.599.953/0001-63 | B262: CAPGEMINI BRASIL LTDA | C262: Capgemini | D262: 46023 | E262: 155816 | F262: 46055 | G262: 37028.02 | H262: 22/12/25 a 21/01/26 | I262: 46115 | J262: INIBANK-611 | K262: P0659891 | L262: MARIIA NIKONOVA | M262: Desenvolvedor Salesforce Sênior | N262: 143.72 | O262: 257.64
A263: 65.599.953/0001-63 | B263: CAPGEMINI BRASIL LTDA | C263: Capgemini | D263: 46023 | E263: 155816 | F263: 46055 | G263: 29323.17 | H263: 22/12/25 a 21/01/26 | I263: 46115 | J263: INIBANK-611 | K263: P0663000 | L263: DIEGO FELIPE SOUZA OLIVEIRA | M263: Desenvolvedor Salesforce Sênior | N263: 144.72 | O263: 202.62
A264: 65.599.953/0001-63 | B264: CAPGEMINI BRASIL LTDA | C264: Capgemini | D264: 46023 | E264: 155816 | F264: 46055 | G264: 32500.25 | H264: 22/12/25 a 21/01/26 | I264: 46115 | J264: INIBANK-611 | K264: P0661715 | L264: MARCEL VALLIM MOREIRA | M264: Desenvolvedor Salesforce Sênior | N264: 160.4 | O264: 202.62
A265: 65.599.953/0001-63 | B265: CAPGEMINI BRASIL LTDA | C265: Capgemini | D265: 46023 | E265: 155816 | F265: 46055 | G265: 48610.8 | H265: 22/12/25 a 21/01/26 | I265: 46115 | J265: INIBANK-611 | K265: P0661361 | L265: FERNANDO DA SILVA TREVISAN | M265: Tech Lead Salesforce | N265: 168 | O265: 289.35
A266: 65.599.953/0001-63 | B266: CAPGEMINI BRASIL LTDA | C266: Capgemini | D266: 46023 | E266: 155800 | F266: 46055 | G266: 50359.68 | H266: 22/12/25 a 21/01/26 | I266: 46115 | J266: INIBANK-611 | K266: P0661574 | L266: LEONARDO LASSANCE | M266: Project Manager | N266: 168 | O266: 299.76
A267: 65.599.953/0001-63 | B267: CAPGEMINI BRASIL LTDA | C267: Capgemini | D267: 46023 | E267: 155809 | F267: 46055 | G267: 21102.99 | H267: 22/12/25 a 21/01/26 | I267: 46115 | J267: INIBANK-611 | K267: P0659790 | L267: Rafael Lucateles Cruz | M267: Consultor UX/UI Sênior | N267: 95.02 | O267: 222.09
A268: 65.599.953/0001-63 | B268: CAPGEMINI BRASIL LTDA | C268: Capgemini | D268: 46023 | E268: 155818 | F268: 46056 | G268: 50082.48 | H268: 22/12/25 a 21/01/26 | I268: 46116 | J268: INIBANK-1173 | K268: P0659788 | L268: RAPHAEL ROSA DE BARROS | M268: Tech Lead Salesforce | N268: 176.77 | O268: 283.32
A269: 65.599.953/0001-63 | B269: CAPGEMINI BRASIL LTDA | C269: Capgemini | D269: 46023 | E269: 155818 | F269: 46056 | G269: 26673.47 | H269: 22/12/25 a 21/01/26 | I269: 46116 | J269: INIBANK-1173 | K269: P0659884 | L269: VICTOR BERNARDES ARAUJO | M269: Desenvolvedor Salesforce Sênior | N269: 103.53 | O269: 257.64
A270: 24.231.517/0001-50 | B270: SYS4B INFORMATICA LTDA | C270: Sys4B | D270: 46023 | E270: 3274 | F270: 46058 | G270: 9472.85 | H270: 22/12/25 a 21/01/26 | I270: 46104 | J270: INIBANK-1173 | K270: P0660057 | L270: Cleiton Lima de Jesus | M270: Desenvolvedor Salesforce Sênior | N270: 160 | O270: 228.58
A271: 24.231.517/0001-50 | B271: SYS4B INFORMATICA LTDA | C271: Sys4B | D271: 46023 | E271: 3274 | F271: 46058 | G271: 36572.8 | H271: 22/12/25 a 21/01/26 | I271: 46104 | J271: INIBANK-1173 | K271: P0662282 | L271: Joyce Andrade | M271: Consultor UX/UI | N271: 47 | O271: 201.55
A272: 24.231.517/0001-50 | B272: SYS4B INFORMATICA LTDA | C272: Sys4B | D272: 46023 | E272: 3276 | F272: 46058 | G272: 33791.46 | H272: 22/12/25 a 21/01/26 | I272: 46104 | J272: INIBANK-611 | K272: P0654694 | L272: Carlos Eduardo Santos Santana | M272: Desenvolvedor Salesforce Sênior | N272: 158 | O272: 213.87
... A290: 24.231.517/0001-50 | B290: SYS4B INFORMATICA LTDA | C290: Sys4B | D290: 46054 | E290: 3297 | F290: 46085 | G290: 28744.13 | H290: 22/01/25 a 21/02/26 | I290: 46131 | J290: INIBANK-1417 | K290: P0000000 | L290: Plantão Salesforce Odin | M290: Desenvolvedor Salesforce Sênior | N290: 0 | O290: 0

Sheet PRESTADOR
A1: MATRICULA | B1: STATUS_PRESTADOR | C1: NOME_PROFISSIONAL | D1: E-MAIL_PORTO | E1: E-MAIL_CONSULTORIA | F1: PAPEL_PRESTADOR | G1: NOME_FANTASIA | H1: INICIATIVA | I1: TIME | J1: HH | K1: ESTIMADO_MENSAL | L1: ESTIMADO_ANUAL
A2: P0659788 | B2: Inativo | C2: Raphael Rosa de Barros | D2: raphael.barros@portoseguro.com.br | E2: raphael.barros@capgemini.com | F2: Tech Lead Salesforce | G2: Capgemini | H2: INIBANK-1173 | I2: Evoluções e Melhorias | J2: 283.32 | K2: 49864.32 | L2: 548507.52
A3: P0659884 | B3: Inativo | C3: Victor Bernardes Araujo | D3: victor.araujo@portoseguro.com.br | E3: victor.b.araujo@capgemini.com | F3: Desenvolvedor Salesforce Sênior | G3: Capgemini | H3: INIBANK-1173 | I3: Evoluções e Melhorias | J3: 257.64 | K3: 45344.64 | L3: 498791.04
A4: P0661738 | B4: Ativo | C4: Erick Delfino Silva | D4: erick.delfino@portoseguro.com.br | E4: erick.silva@capgemini.com | F4: Analista de Teste Sênior | G4: Capgemini | H4: INIBANK-1173 | I4: Evoluções e Melhorias | J4: 193.74 | K4: 34098.24 | L4: 375080.64
A5: P0661166 | B5: Inativo | C5: Adejailson Antonio De Luna | D5: adejailson.luna@portoseguro.com.br | E5: adejailson.luna@meta.com.br | F5: Product Owner | G5: Meta | H5: INIBANK-1173 | I5: Evoluções e Melhorias | J5: 192.88 | K5: 33946.88 | L5: 373415.68
A6: P0660057 | B6: Ativo | C6: Cleiton Lima de Jesus | D6: cleiton.jesus@portoseguro.com.br | E6: cleiton.jesus@sys4b.com.br | F6: Desenvolvedor Salesforce Sênior | G6: Sys4B | H6: INIBANK-1173 | I6: Evoluções e Melhorias | J6: 228.58 | K6: 40230.08 | L6: 442530.88
A7: P0656797 | B7: Ativo | C7: Gustavo Seiji Onizuka | D7: gustavo.onizuka@portoseguro.com.br | E7: gustavo.s.onizuka@sys4b.com.br | F7: Desenvolvedor Salesforce | G7: Sys4B | H7: INIBANK-1173 | I7: Evoluções e Melhorias | J7: 213.87 | K7: 37641.12 | L7: 414052.32
A8: P0658519 | B8: Ativo | C8: Leonardo Lins | D8: leonardo.lins@portoseguro.com.br | E8: leonardo.silva@sys4b.com.br | F8: Desenvolvedor Salesforce Sênior | G8: Sys4B | H8: INIBANK-1173 | I8: Evoluções e Melhorias | J8: 213.87 | K8: 37641.12 | L8: 414052.32
A9: P0662282 | B9: Inativo | C9: Joyce Andrade | D9: joyce.barretosouza@portoseguro.com.br | E9: joyce.souza@sys4b.com.br | F9: Consultor UX/UI | G9: Sys4B | H9: INIBANK-1173 | I9: Evoluções e Melhorias | J9: 201.4 | K9: 35446.4 | L9: 389910.4
A10: P0661574 | B10: Ativo | C10: Leonardo Lassance | D10: leonardo.lassance@portoseguro.com.br | E10: leonardo.lassance@capgemini.com | F10: Project Manager | G10: Capgemini | H10: INIBANK-1173 | I10: Evoluções e Melhorias | J10: 299.76 | K10: 52757.76 | L10: 580335.36
A11: P0659891 | B11: Inativo | C11: Mariia Nikonova | D11: mariia.nikonova@portoseguro.com.br | E11: mariia.nikonova@capgemini.com | F11: Desenvolvedor Salesforce Sênior | G11: Capgemini | H11: INIBANK-611 | I11: Novos Projetos | J11: 257.64 | K11: 45344.64 | L11: 498791.04
A12: P0661361 | B12: Ativo | C12: Fernando da Silva Trevisan | D12: fernando.trevisan@portoseguro.com.br | E12: fernando.trevisan@capgemini.com | F12: Tech Lead Salesforce | G12: Capgemini | H12: INIBANK-1173 | I12: Evoluções e Melhorias | J12: 289.35 | K12: 50925.6 | L12: 560181.6
A13: P0661715 | B13: Ativo | C13: Marcel Vallim Moreira | D13: marcel.moreira@portoseguro.com.br | E13: marcel.moreira@capgemini.com | F13: Desenvolvedor Salesforce Sênior | G13: Capgemini | H13: INIBANK-1173 | I13: Evoluções e Melhorias | J13: 202.62 | K13: 35661.12 | L13: 392272.32
... A15: P0659790 | B15: Inativo | C15: Rafael Lucateles Cruz | D15: rafael.lucateles@portoseguro.com.br | E15: rafael.a.cruz@capgemini.com | F15: Consultor UX/UI Sênior | G15: Capgemini | H15: INIBANK-611 | I15: Novos Projetos | J15: 222.09 | K15: 39087.84 | L15: 429966.24
A16: P0659934 | B16: Inativo | C16: Jorge Cardoso Filho | D16: jorge.filho@portoseguro.com.br | F16: Analista de Teste | G16: GFT | H16: INIBANK-611 | I16: Novos Projetos | J16: 184.6 | K16: 32489.6 | L16: 357385.6
A17: P0654694 | B17: Ativo | C17: Carlos Eduardo Santos Santana | D17: carloseduardo.santos@portoseguro.com.br | E17: carlos.santana@sys4b.com.br | F17: Desenvolvedor Salesforce Sênior | G17: Sys4B | H17: INIBANK-1173 | I17: Evoluções e Melhorias | J17: 213.87 | K17: 37641.12 | L17: 414052.32
A18: P0662312 | B18: Ativo | C18: Francielle Thiezo Revesso Pinto | D18: francielle.pinto@portoseguro.com.br | E18: francielle.revesso@sys4b.com.br | F18: Administrador Salesforce | G18: Sys4B | H18: INIBANK-1417 | I18: Plataforma Salesforce Odin | J18: 213.87 | K18: 37641.12 | L18: 414052.32
A19: P0650648 | B19: Ativo | C19: Lucas Takita | D19: lucas.takita@portoseguro.com.br | E19: lucas.takita@infinitysys.com.br | F19: Desenvolvedor Salesforce Sênior | G19: Sys4B | H19: INIBANK-1417 | I19: Plataforma Salesforce Odin | J19: 213.87 | K19: 37641.12 | L19: 414052.32
A20: P0663654 | B20: Ativo | C20: Gabriel Costa Datovo Inoue Maekawa | D20: gabriel.maekawa@portoseguro.com.br | E20: gabriel.montalbini@sys4b.com.br | F20: Desenvolvedor Pleno | G20: Sys4B | H20: INIBANK-1417 | I20: Plataforma Salesforce Odin | J20: 191.36 | K20: 33679.36 | L20: 370472.96
A21: P0000000 | B21: Ativo | C21: Plantão Salesforce Odin | F21: Desenvolvedor Salesforce Sênior | G21: Sys4B | H21: INIBANK-1417 | I21: Plataforma Salesforce Odin | J21: 213.87 | K21: 40000 | L21: 480000

Sheet FORECAST
A1: INICIATIVA | B1: INICIATIVA_DESCRICAO | C1: INICIATIVA_TIPO | D1: INICIATIVA_DIREÇÃO | E1: TOTAL_FORECAST | F1: 46023 | G1: 46054 | H1: 46082 | I1: 46113 | J1: 46143 | K1: 46174 | L1: 46204 | M1: 46235 | N1: 46266 | O1: 46296 | P1: 46327 | Q1: 46357
A2: INIBANK-54 | B2: Evoluções Salesforce para o Cartão | C2: Forecast | D2: Soma | E2: =SUM(F2:Q2) -> 0 | F2: 0 | G2: 0 | H2: 0 | I2: 0 | J2: 0 | K2: 0 | L2: 0 | M2: 0 | N2: 0 | O2: 0 | P2: 0 | Q2: 0
A3: INIBANK-226 | B3: Evoluções e Melhorias | C3: Forecast | D3: Soma | E3: =SUM(F3:Q3) -> 0 | F3: 0 | G3: 0 | H3: 0 | I3: 0 | J3: 0 | K3: 0 | L3: 0 | M3: 0 | N3: 0 | O3: 0 | P3: 0 | Q3: 0
A4: INIBANK-611 | B4: Implantação do SalesForce para Central de Atendimento de Clientes PJ | C4: Forecast | D4: Soma | E4: =SUM(F4:Q4) -> 0 | F4: 0 | G4: 0 | H4: 0 | I4: 0 | J4: 0 | K4: 0 | L4: 0 | M4: 0 | N4: 0 | O4: 0 | P4: 0 | Q4: 0
A5: INIBANK-289 | B5: Sustentação Atendimento Salesforce Odin | C5: Forecast | D5: Soma | E5: =SUM(F5:Q5) -> 0 | F5: 0 | G5: 0 | H5: 0 | I5: 0 | J5: 0 | K5: 0 | L5: 0 | M5: 0 | N5: 0 | O5: 0 | P5: 0 | Q5: 0
A6: INIBANK-1417 | B6: [Sustentação] Atendimento / Salesforce | C6: Forecast | D6: Soma | E6: =SUM(F6:Q6) -> 1865718 | F6: 155476.5 | G6: 155476.5 | H6: 155476.5 | I6: 155476.5 | J6: 155476.5 | K6: 155476.5 | L6: 155476.5 | M6: 155476.5 | N6: 155476.5 | O6: 155476.5 | P6: 155476.5 | Q6: 155476.5
A7: INIBANK-1173 | B7: [Book] Squad Salesforce (Atendimento) | C7: Forecast | D7: Soma | E7: =SUM(F7:Q7) -> 3955366 | F7: 329613.83 | G7: 329613.83 | H7: 329613.83 | I7: 329613.83 | J7: 329613.83 | K7: 329613.83 | L7: 329613.83 | M7: 329613.83 | N7: 329613.83 | O7: 329613.83 | P7: 329613.83 | Q7: 329613.83
A8: INIBANK-1173 | B8: [Book] Squad Salesforce (Atendimento) - Adicional Postergação NF 2025/2026 | C8: Adicional Forecast | D8: Soma | E8: =SUM(F8:Q8) -> 196499 | F8: 196499 | G8: 0 | H8: 0 | I8: 0 | J8: 0 | K8: 0 | L8: 0 | M8: 0 | N8: 0 | O8: 0 | P8: 0 | Q8: 0
A9: INIBANK-1349 | B9: Atendimento INVEST BANK - MVP | C9: Forecast | D9: Soma | E9: =SUM(F9:Q9) -> 100000 | F9: 100000 | G9: 0 | H9: 0 | I9: 0 | J9: 0 | K9: 0 | L9: 0 | M9: 0 | N9: 0 | O9: 0 | P9: 0 | Q9: 0
A10: INIBANK-1349 | B10: Atendimento INVEST BANK - SAC + SEGMENTACÃO + PERMISSIONAMENTO | C10: Adicional Forecast | D10: Soma | E10: =SUM(F10:Q10) -> 90000 | F10: 0 | G10: 0 | H10: 45000 | I10: 45000 | J10: 0 | K10: 0 | L10: 0 | M10: 0 | N10: 0 | O10: 0 | P10: 0 | Q10: 0
A11: INIBANK-1173 | B11: [Book] Squad Salesforce (Atendimento) | C11: Redução Forecast | D11: Subtrai | E11: =SUM(F11:Q11) -> 2400000 | F11: 0 | G11: 0 | H11: 0 | I11: 0 | J11: 300000 | K11: 300000 | L11: 300000 | M11: 300000 | N11: 300000 | O11: 300000 | P11: 300000 | Q11: 300000

Sheet HISTOGRAMA
A1: MATRICULA | B1: STATUS_PRESTADOR | C1: NOME_PROFISSIONAL | D1: PAPEL_PRESTADOR | E1: NOME_FANTASIA | F1: INICIATIVA | G1: TIME | H1: HH | I1: ESTIMADO_MENSAL | J1: ESTIMADO_ANUAL | K1: 46023 | L1: 46054 | M1: 46082 | N1: 46113 | O1: 46143 | P1: 46174 | Q1: 46204 | R1: 46235 | S1: 46266 | T1: 46296 | U1: 46327 | V1: 46357
A2: P0659788 | B2: Inativo | C2: Raphael Rosa de Barros | D2: Tech Lead Salesforce | E2: Capgemini | F2: INIBANK-1173 | G2: Evoluções e Melhorias | H2: 283.32 | I2: =H2*176 -> 49864.32 | J2: =I2*11 -> 548507.52 | K2: 0 | L2: 0 | M2: 0 | N2: 0 | O2: 0 | P2: 0 | Q2: 0 | R2: 0 | S2: 0 | T2: 0 | U2: 0 | V2: 0
A3: P0659884 | B3: Inativo | C3: Victor Bernardes Araujo | D3: Desenvolvedor Salesforce Sênior | E3: Capgemini | F3: INIBANK-1173 | G3: Evoluções e Melhorias | H3: 257.64 | I3: =H3*176 -> 45344.64 | J3: =I3*11 -> 498791.04 | K3: 0 | L3: 0 | M3: 0 | N3: 0 | O3: 0 | P3: 0 | Q3: 0 | R3: 0 | S3: 0 | T3: 0 | U3: 0 | V3: 0
A4: P0661738 | B4: Ativo | C4: Erick Delfino Silva | D4: Analista de Teste Sênior | E4: Capgemini | F4: INIBANK-1173 | G4: Evoluções e Melhorias | H4: 193.74 | I4: =H4*176 -> 34098.24 | J4: =I4*11 -> 375080.64 | K4: 1 | L4: 1 | M4: 1 | N4: 0.5 | O4: 0 | P4: 0 | Q4: 0 | R4: 0 | S4: 0 | T4: 0 | U4: 0 | V4: 0
A5: P0661166 | B5: Inativo | C5: Adejailson Antonio De Luna | D5: Product Owner | E5: Meta | F5: INIBANK-1173 | G5: Evoluções e Melhorias | H5: 192.88 | I5: =H5*176 -> 33946.88 | J5: =I5*11 -> 373415.68 | K5: 0 | L5: 0 | M5: 0 | N5: 0 | O5: 0 | P5: 0 | Q5: 0 | R5: 0 | S5: 0 | T5: 0 | U5: 0 | V5: 0
A6: P0660057 | B6: Ativo | C6: Cleiton Lima de Jesus | D6: Desenvolvedor Salesforce Sênior | E6: Sys4B | F6: INIBANK-1173 | G6: Evoluções e Melhorias | H6: 228.58 | I6: =H6*176 -> 40230.08 | J6: =I6*11 -> 442530.88 | K6: 1 | L6: 1 | M6: 1 | N6: 1 | O6: 1 | P6: 1 | Q6: 1 | R6: 1 | S6: 1 | T6: 1 | U6: 1 | V6: 1
A7: P0656797 | B7: Ativo | C7: Gustavo Seiji Onizuka | D7: Desenvolvedor Salesforce | E7: Sys4B | F7: INIBANK-1173 | G7: Evoluções e Melhorias | H7: 213.87 | I7: =H7*176 -> 37641.12 | J7: =I7*11 -> 414052.32 | K7: 1 | L7: 1 | M7: 1 | N7: 0.5 | O7: 0 | P7: 0 | Q7: 0 | R7: 0 | S7: 0 | T7: 0 | U7: 0 | V7: 0
A8: P0658519 | B8: Ativo | C8: Leonardo Lins | D8: Desenvolvedor Salesforce Sênior | E8: Sys4B | F8: INIBANK-1173 | G8: Evoluções e Melhorias | H8: 213.87 | I8: =H8*176 -> 37641.12 | J8: =I8*11 -> 414052.32 | K8: 1 | L8: 1 | M8: 1 | N8: 1 | O8: 1 | P8: 1 | Q8: 1 | R8: 1 | S8: 1 | T8: 1 | U8: 1 | V8: 1
A9: P0662282 | B9: Inativo | C9: Joyce Andrade | D9: Consultor UX/UI | E9: Sys4B | F9: INIBANK-1173 | G9: Evoluções e Melhorias | H9: 201.4 | I9: =H9*176 -> 35446.4 | J9: =I9*11 -> 389910.4 | K9: 0 | L9: 0 | M9: 0 | N9: 0 | O9: 0 | P9: 0 | Q9: 0 | R9: 0 | S9: 0 | T9: 0 | U9: 0 | V9: 0
A10: P0661574 | B10: Ativo | C10: Leonardo Lassance | D10: Project Manager | E10: Capgemini | F10: INIBANK-1173 | G10: Evoluções e Melhorias | H10: 299.76 | I10: =H10*176 -> 52757.76 | J10: =I10*11 -> 580335.36 | K10: 1 | L10: 1 | M10: 1 | N10: 0.5 | O10: 0 | P10: 0 | Q10: 0 | R10: 0 | S10: 0 | T10: 0 | U10: 0 | V10: 0
A11: P0659891 | B11: Inativo | C11: Mariia Nikonova | D11: Desenvolvedor Salesforce Sênior | E11: Capgemini | F11: INIBANK-611 | G11: Novos Projetos | H11: 257.64 | I11: =H11*176 -> 45344.64 | J11: =I11*11 -> 498791.04 | K11: 0 | L11: 0 | M11: 0 | N11: 0 | O11: 0 | P11: 0 | Q11: 0 | R11: 0 | S11: 0 | T11: 0 | U11: 0 | V11: 0
A12: P0661361 | B12: Ativo | C12: Fernando da Silva Trevisan | D12: Tech Lead Salesforce | E12: Capgemini | F12: INIBANK-1173 | G12: Evoluções e Melhorias | H12: 289.35 | I12: =H12*176 -> 50925.6 | J12: =I12*11 -> 560181.6 | K12: 1 | L12: 1 | M12: 1 | N12: 0.5 | O12: 0 | P12: 0 | Q12: 0 | R12: 0 | S12: 0 | T12: 0 | U12: 0 | V12: 0
A13: P0661715 | B13: Ativo | C13: Marcel Vallim Moreira | D13: Desenvolvedor Salesforce Sênior | E13: Capgemini | F13: INIBANK-1173 | G13: Evoluções e Melhorias | H13: 202.62 | I13: =H13*176 -> 35661.12 | J13: =I13*11 -> 392272.32 | K13: 1 | L13: 1 | M13: 1 | N13: 0.5 | O13: 0 | P13: 0 | Q13: 0 | R13: 0 | S13: 0 | T13: 0 | U13: 0 | V13: 0
... A20: P0663654 | B20: Ativo | C20: Gabriel Costa Datovo Inoue Maekawa | D20: Desenvolvedor Pleno | E20: Sys4B | F20: INIBANK-1417 | G20: Plataforma Salesforce Odin | H20: 191.36 | I20: =H20*176 -> 33679.36 | J20: =I20*11 -> 370472.96 | K20: 1 | L20: 1 | M20: 1 | N20: 1 | O20: 1 | P20: 1 | Q20: 1 | R20: 1 | S20: 1 | T20: 1 | U20: 1 | V20: 1
A21: P0000000 | B21: Ativo | C21: Plantão Salesforce Odin | D21: Desenvolvedor Salesforce Sênior | E21: Sys4B | F21: INIBANK-1417 | G21: Plataforma Salesforce Odin | H21: 213.87 | I21: 40000 | J21: =I21*12 -> 480000 | K21: 1 | L21: 1 | M21: 1 | N21: 1 | O21: 1 | P21: 1 | Q21: 1 | R21: 1 | S21: 1 | T21: 1 | U21: 1 | V21: 1

Sheet ORÇAMENTO 2026 v1
A1: Nome Prestador | B1: e-mail Porto | C1: e-mail Consultoria | D1: Matrícula | E1: Papel | F1: Consultoria | G1: Time | H1: R$ H/h | I1: Estimado Mensal | J1: Estimado até Dez/25 | K1: Iniciativa
A2: Adejailson Antonio De Luna | B2: adejailson.luna@portoseguro.com.br | C2: adejailson.luna@meta.com.br | D2: P0661166 | E2: Product Owner | F2: Meta | G2: Evoluções e Melhorias | H2: 192.88 | I2: =H2*176 -> 33946.88 | J2: =I2*12 -> 407362.56 | K2: INIBANK-1173
A3: Raphael Rosa de Barros | B3: raphael.barros@portoseguro.com.br | C3: raphael.barros@capgemini.com | D3: P0659788 | E3: Tech Lead Salesforce | F3: Capgemini | G3: Evoluções e Melhorias | H3: 283.32 | I3: =H3*176 -> 49864.32 | J3: =I3*12 -> 598371.84 | K3: INIBANK-1173
A4: Victor Bernardes Araujo | B4: victor.araujo@portoseguro.com.br | C4: victor.b.araujo@capgemini.com | D4: P0659884 | E4: Desenvolvedor Salesforce Sênior | F4: Capgemini | G4: Evoluções e Melhorias | H4: 257.64 | I4: =H4*176 -> 45344.64 | J4: =I4*12 -> 544135.68 | K4: INIBANK-1173
A5: Mariia Nikonova | B5: mariia.nikonova@portoseguro.com.br | C5: mariia.nikonova@capgemini.com | D5: P0659891 | E5: Desenvolvedor Salesforce Sênior | F5: Capgemini | G5: Novos Projetos | H5: 257.64 | I5: =H5*176 -> 45344.64 | J5: =I5*12 -> 544135.68 | K5: INIBANK-611
A6: Diego Felipe Souza Oliveira | B6: diego.felipeoliveira@portoseguro.com.br | C6: diego.a.oliveira@capgemini.com | D6: P0663000 | E6: Desenvolvedor Salesforce Sênior | F6: Capgemini | G6: Novos Projetos | H6: 202.62 | I6: =H6*176 -> 35661.12 | J6: =I6*12 -> 427933.44 | K6: INIBANK-611
A7: Rafael Lucateles Cruz | B7: rafael.lucateles@portoseguro.com.br | C7: rafael.a.cruz@capgemini.com | D7: P0659790 | E7: Consultor UX/UI Sênior | F7: Capgemini | G7: Novos Projetos | H7: 222.09 | I7: =H7*176 -> 39087.84 | J7: =I7*12 -> 469054.08 | K7: INIBANK-611
A8: Joyce Andrade | B8: joyce.barretosouza@portoseguro.com.br | C8: joyce.souza@sys4b.com.br | D8: P0662282 | E8: Consultor UX/UI | F8: Sys4B | G8: Evoluções e Melhorias | H8: 201.4 | I8: =H8*176 -> 35446.4 | J8: =I8*12 -> 425356.8 | K8: INIBANK-1173
A9: Jorge Cardoso Filho | B9: jorge.filho@portoseguro.com.br | D9: P0659934 | E9: Analista de Teste | F9: GFT | G9: Novos Projetos | H9: 184.6 | I9: =H9*176 -> 32489.6 | J9: =I9*12 -> 389875.2 | K9: INIBANK-611
J10: =SUM(J2:J9) -> 3806225.3
A13: Leonardo Lassance | B13: leonardo.lassance@portoseguro.com.br | C13: leonardo.lassance@capgemini.com | D13: P0661574 | E13: Project Manager | F13: Capgemini | G13: Novos Projetos | H13: 283.32 | I13: =H13*176 -> 49864.32 | J13: =I13*12 -> 598371.84 | K13: INIBANK-611
A14: Fernando da Silva Trevisan | B14: fernando.trevisan@portoseguro.com.br | C14: fernando.trevisan@capgemini.com | D14: P0661361 | E14: Tech Lead Salesforce | F14: Capgemini | G14: Novos Projetos | H14: 283.32 | I14: =H14*176 -> 49864.32 | J14: =I14*12 -> 598371.84 | K14: INIBANK-611
A15: Cleiton Lima de Jesus | B15: cleiton.jesus@portoseguro.com.br | C15: cleiton.jesus@sys4b.com.br | D15: P0660057 | E15: Desenvolvedor Salesforce Sênior | F15: Sys4B | G15: Evoluções e Melhorias | H15: 223 | I15: =H15*176 -> 39248 | J15: =I15*12 -> 470976 | K15: INIBANK-1173
A16: Leonardo Lins | B16: leonardo.lins@portoseguro.com.br | C16: leonardo.silva@sys4b.com.br | D16: P0658519 | E16: Desenvolvedor Salesforce Sênior | F16: Sys4B | G16: Evoluções e Melhorias | H16: 208.65 | I16: =H16*176 -> 36722.4 | J16: =I16*12 -> 440668.8 | K16: INIBANK-1173
A17: Marcel Vallim Moreira | B17: marcel.moreira@portoseguro.com.br | C17: marcel.moreira@capgemini.com | D17: P0661715 | E17: Desenvolvedor Salesforce Sênior | F17: Capgemini | G17: Novos Projetos | H17: 202.62 | I17: =H17*176 -> 35661.12 | J17: =I17*12 -> 427933.44 | K17: INIBANK-611
A18: Carlos Eduardo Santos Santana | B18: carloseduardo.santos@portoseguro.com.br | C18: carlos.santana@sys4b.com.br | D18: P0654694 | E18: Desenvolvedor Salesforce Sênior | F18: Sys4B | G18: Novos Projetos | H18: 208.65 | I18: =H18*176 -> 36722.4 | J18: =I18*12 -> 440668.8 | K18: INIBANK-611
A19: Erick Delfino Silva | B19: erick.delfino@portoseguro.com.br | C19: erick.silva@capgemini.com | D19: P0661738 | E19: Analista de Teste Sênior | F19: Capgemini | G19: Evoluções e Melhorias | H19: 193.74 | I19: =H19*176 -> 34098.24 | J19: =I19*12 -> 409178.88 | K19: INIBANK-1173
J20: =SUM(J13:J19) -> 3386169.6
A21: Gustavo Seiji Onizuka | B21: gustavo.onizuka@portoseguro.com.br | C21: gustavo.s.onizuka@sys4b.com.br | D21: P0656797 | E21: Desenvolvedor Salesforce | F21: Sys4B | G21: Evoluções e Melhorias | H21: 208.65 | I21: =H21*176 -> 36722.4 | J21: =I21*12 -> 440668.8 | K21: INIBANK-1173
J22: =J20+J21 -> 3826838.4
A25: Francielle Thiezo Revesso Pinto | B25: francielle.pinto@portoseguro.com.br | C25: francielle.revesso@sys4b.com.br | D25: P0662312 | E25: Administrador Salesforce | F25: Sys4B | G25: Plataforma Salesforce Odin | H25: 208.65 | I25: =H25*176 -> 36722.4 | J25: =I25*12 -> 440668.8 | K25: INIBANK-289
A26: Lucas Takita | B26: lucas.takita@portoseguro.com.br | C26: lucas.takita@infinitysys.com.br | D26: P0650648 | E26: Desenvolvedor Salesforce Sênior | F26: Sys4B | G26: Plataforma Salesforce Odin | H26: 208.65 | I26: =H26*176 -> 36722.4 | J26: =I26*12 -> 440668.8 | K26: INIBANK-289
A27: Gabriel Costa Datovo Inoue Maekawa | B27: gabriel.maekawa@portoseguro.com.br | C27: gabriel.montalbini@sys4b.com.br | D27: P0663654 | E27: Desenvolvedor Pleno | F27: Sys4B | G27: Plataforma Salesforce Odin | H27: 208.65 | I27: =H27*176 -> 36722.4 | J27: =I27*12 -> 440668.8 | K27: INIBANK-289
A28: Plantão Salesforce Odin + OverTime | D28: P0000000 | E28: Desenvolvedor Salesforce Sênior | F28: Sys4B | G28: Plataforma Salesforce Odin | H28: 208.65 | I28: 40000 | J28: =I28*12 -> 480000 | K28: INIBANK-289
J29: =SUM(J25:J28) -> 1802006.4

Sheet ORÇAMENTO 2026 v2
A1: Nome Prestador | B1: e-mail Porto | C1: e-mail Consultoria | D1: Matrícula | E1: Papel | F1: Consultoria | G1: Time | H1: R$ H/h | I1: Estimado Mensal | J1: Estimado até Dez/25 | K1: Estimado 11 meses | L1: Iniciativa
A3: Leonardo Lassance | B3: leonardo.lassance@portoseguro.com.br | C3: leonardo.lassance@capgemini.com | D3: P0661574 | E3: Project Manager | F3: Capgemini | G3: Novos Projetos | H3: 299.76 | I3: =H3*176 -> 52757.76 | J3: =I3*12 -> 633093.12 | K3: =I3*11 -> 580335.36 | L3: INIBANK-1173
A4: Fernando da Silva Trevisan | B4: fernando.trevisan@portoseguro.com.br | C4: fernando.trevisan@capgemini.com | D4: P0661361 | E4: Tech Lead Salesforce | F4: Capgemini | G4: Novos Projetos | H4: 289.35 | I4: =H4*176 -> 50925.6 | J4: =I4*12 -> 611107.2 | K4: =I4*11 -> 560181.6 | L4: INIBANK-1173
A5: Cleiton Lima de Jesus | B5: cleiton.jesus@portoseguro.com.br | C5: cleiton.jesus@sys4b.com.br | D5: P0660057 | E5: Desenvolvedor Salesforce | F5: Sys4B | G5: Evoluções e Melhorias | H5: 228.58 | I5: =H5*176 -> 40230.08 | J5: =I5*12 -> 482760.96 | K5: =I5*11 -> 442530.88 | L5: INIBANK-1173
A6: Gustavo Seiji Onizuka | B6: gustavo.onizuka@portoseguro.com.br | C6: gustavo.s.onizuka@sys4b.com.br | D6: P0656797 | E6: Desenvolvedor Salesforce | F6: Sys4B | G6: Evoluções e Melhorias | H6: 213.87 | I6: =H6*176 -> 37641.12 | J6: =I6*12 -> 451693.44 | K6: =I6*11 -> 414052.32 | L6: INIBANK-1173
A7: Leonardo Lins | B7: leonardo.lins@portoseguro.com.br | C7: leonardo.silva@sys4b.com.br | D7: P0658519 | E7: Desenvolvedor Salesforce | F7: Sys4B | G7: Evoluções e Melhorias | H7: 213.87 | I7: =H7*176 -> 37641.12 | J7: =I7*12 -> 451693.44 | K7: =I7*11 -> 414052.32 | L7: INIBANK-1173
A8: Marcel Vallim Moreira | B8: marcel.moreira@portoseguro.com.br | C8: marcel.moreira@capgemini.com | D8: P0661715 | E8: Desenvolvedor Salesforce | F8: Capgemini | G8: Novos Projetos | H8: 202.62 | I8: =H8*176 -> 35661.12 | J8: =I8*12 -> 427933.44 | K8: =I8*11 -> 392272.32 | L8: INIBANK-1173
A9: Carlos Eduardo Santos Santana | B9: carloseduardo.santos@portoseguro.com.br | C9: carlos.santana@sys4b.com.br | D9: P0654694 | E9: Desenvolvedor Salesforce | F9: Sys4B | G9: Novos Projetos | H9: 213.87 | I9: =H9*176 -> 37641.12 | J9: =I9*12 -> 451693.44 | K9: =I9*11 -> 414052.32 | L9: INIBANK-1173
A10: Erick Delfino Silva | B10: erick.delfino@portoseguro.com.br | C10: erick.silva@capgemini.com | D10: P0661738 | E10: Analista de Teste | F10: Capgemini | G10: Evoluções e Melhorias | H10: 193.74 | I10: =H10*176 -> 34098.24 | J10: =I10*12 -> 409178.88 | K10: =I10*11 -> 375080.64 | L10: INIBANK-1173
J11: =SUM(J3:J10) -> 3919153.9 | K11: =SUM(K3:K10) -> 3592557.8
A14: Francielle Thiezo Revesso Pinto | B14: francielle.pinto@portoseguro.com.br | C14: francielle.revesso@sys4b.com.br | D14: P0662312 | E14: Administrador Salesforce | F14: Sys4B | G14: Plataforma Salesforce Odin | H14: 213.87 | I14: =H14*176 -> 37641.12 | J14: =I14*12 -> 451693.44 | K14: =I14*11 -> 414052.32 | L14: INIBANK-289
A15: Lucas Takita | B15: lucas.takita@portoseguro.com.br | C15: lucas.takita@infinitysys.com.br | D15: P0650648 | E15: Desenvolvedor Salesforce Sênior | F15: Sys4B | G15: Plataforma Salesforce Odin | H15: 213.87 | I15: =H15*176 -> 37641.12 | J15: =I15*12 -> 451693.44 | K15: =I15*11 -> 414052.32 | L15: INIBANK-289
A16: Gabriel Costa Datovo Inoue Maekawa | B16: gabriel.maekawa@portoseguro.com.br | C16: gabriel.montalbini@sys4b.com.br | D16: P0663654 | E16: Desenvolvedor Pleno | F16: Sys4B | G16: Plataforma Salesforce Odin | H16: 213.87 | I16: =H16*176 -> 37641.12 | J16: =I16*12 -> 451693.44 | K16: =I16*11 -> 414052.32 | L16: INIBANK-289
A17: Plantão Salesforce Odin + OverTime | D17: P0000000 | E17: Desenvolvedor Salesforce Sênior | F17: Sys4B | G17: Plataforma Salesforce Odin | H17: 213.87 | I17: 40000 | J17: =I17*12 -> 480000 | K17: =I17*11 -> 440000 | L17: INIBANK-289
J18: =SUM(J14:J17) -> 1835080.3 | K18: =SUM(K14:K17) -> 1682157

Sheet RATE_CARD
A1: Sys4B | C1: Estimado Mensal | D1: Estimado Anual
A2: Salesforce Developer Jr | B2: 164.72 | C2: =B2*176 -> 28990.72 | D2: =C2*12 -> 347888.64
A3: Salesforce Developer Pleno | B3: 186.69 | C3: =B3*176 -> 32857.44 | D3: =C3*12 -> 394289.28
A4: Salesforce Developer Senior | B4: 208.65 | C4: =B4*176 -> 36722.4 | D4: =C4*12 -> 440668.8
A5: Salesforce Tech Lead | B5: 223 | C5: =B5*176 -> 39248 | D5: =C5*12 -> 470976
A6: Consultor UX/UI | B6: 201.4 | C6: =B6*176 -> 35446.4 | D6: =C6*12 -> 425356.8
A9: Capgemini
A10: Salesforce Developer Jr | B10: 108.86 | C10: =B10*176 -> 19159.36 | D10: =C10*12 -> 229912.32
A11: Salesforce Developer Pleno | B11: 149.38 | C11: =B11*176 -> 26290.88 | D11: =C11*12 -> 315490.56
A12: Salesforce Developer Senior | B12: 202.62 | C12: =B12*176 -> 35661.12 | D12: =C12*12 -> 427933.44
A13: Salesforce Funcional Jr | B13: 149.38 | C13: =B13*176 -> 26290.88 | D13: =C13*12 -> 315490.56
A14: Salesforce Funcional Pleno | B14: 202.62 | C14: =B14*176 -> 35661.12 | D14: =C14*12 -> 427933.44
A15: Salesforce Funcional Senior | B15: 257.64 | C15: =B15*176 -> 45344.64 | D15: =C15*12 -> 544135.68
A16: Salesforce Tech Lead | B16: 283.32 | C16: =B16*176 -> 49864.32 | D16: =C16*12 -> 598371.84
A17: Project Manager | B17: 283.32 | C17: =B17*176 -> 49864.32 | D17: =C17*12 -> 598371.84
A18: Consultor UX/UI Sênior | B18: 222.09 | C18: =B18*176 -> 39087.84 | D18: =C18*12 -> 469054.08
A19: Analista de Teste Sênior | B19: 193.74 | C19: =B19*176 -> 34098.24 | D19: =C19*12 -> 409178.88
A22: OSF Digital
A23: Salesforce Developer Jr | B23: 195.08 | C23: =B23*176 -> 34334.08 | D23: =C23*12 -> 412008.96
A24: Salesforce Developer Pleno I | B24: 229.5 | C24: =B24*176 -> 40392 | D24: =C24*12 -> 484704
A25: Salesforce Developer Pleno II | B25: 246.03 | C25: =B25*176 -> 43301.28 | D25: =C25*12 -> 519615.36
A26: Salesforce Developer Senior | B26: 286.88 | C26: =B26*176 -> 50490.88 | D26: =C26*12 -> 605890.56
A31: GFT
A32: Salesforce Developer Jr | B32: 101.35 | C32: =B32*176 -> 17837.6 | D32: =C32*12 -> 214051.2
A33: Salesforce Developer Pleno | B33: 140.53 | C33: =B33*176 -> 24733.28 | D33: =C33*12 -> 296799.36
A34: Salesforce Developer Senior | B34: 184.03 | C34: =B34*176 -> 32389.28 | D34: =C34*12 -> 388671.36
A35: Salesforce Developer Especialista | B35: 271.62 | C35: =B35*176 -> 47805.12 | D35: =C35*12 -> 573661.44
A36: Salesforce Funcional Jr | B36: 128.65 | C36: =B36*176 -> 22642.4 | D36: =C36*12 -> 271708.8
A37: Salesforce Funcional Pleno | B37: 168.46 | C37: =B37*176 -> 29648.96 | D37: =C37*12 -> 355787.52
A38: Salesforce Funcional Senior | B38: 242.7 | C38: =B38*176 -> 42715.2 | D38: =C38*12 -> 512582.4
A39: Salesforce Funcional Especialista | B39: 273.65 | C39: =B39*176 -> 48162.4 | D39: =C39*12 -> 577948.8
A40: Salesforce Tech Lead Pleno | B40: 167.25 | C40: =B40*176 -> 29436 | D40: =C40*12 -> 353232
A41: Salesforce Tech Lead Senior | B41: 210.81 | C41: =B41*176 -> 37102.56 | D41: =C41*12 -> 445230.72
A42: Salesforce Tech Lead Especialista | B42: 221.96 | C42: =B42*176 -> 39064.96 | D42: =C42*12 -> 468779.52
A43: Analista de Teste Jr | B43: 66.19 | C43: =B43*176 -> 11649.44 | D43: =C43*12 -> 139793.28
... A46: Analista de Teste Especialista | B46: 222.97 | C46: =B46*176 -> 39242.72 | D46: =C46*12 -> 470912.64
A50: ZUP
A51: PERFIL | B51: Júnior (R$) | C51: Pleno (R$) | D51: Sênior (R$) | E51: Especialista (R$)
A52: Agile | B52: 166.79 | C52: 187.62 | D52: 269.73 | E52: 340.76
A53: Analista de Automação de Testes | B53: 121.15 | C53: 176.82 | D53: 232.93 | E53: 354.93
A54: Analista de Dados | B54: 129.41 | C54: 170.67 | D54: 250.72 | E54: 330.54
A55: Analista de Negócios | B55: 128.88 | C55: 193.71 | D55: 291.54 | E55: 378.39
A56: Analista de Sistemas | B56: 125.02 | C56: 202.85 | D56: 292.7 | E56: 367.04
A57: Arquiteto | B57: 128.85 | C57: 180.39 | D57: 280.98 | E57: 356.85
A58: Arquiteto de Salesforce | B58: 0 | C58: 0 | D58: 297.32 | E58: 397.84
A59: Arquiteto SAP | B59: 0 | C59: 0 | D59: 297.32 | E59: 397.84
A60: Back End | B60: 125.1 | C60: 159.14 | D60: 209.64 | E60: 354.93
A61: Cientista de Dados | B61: 115.03 | C61: 158.72 | D61: 250.72 | E61: 326.99
A62: Consultor | B62: 0 | C62: 0 | D62: 0 | E62: 692.25
A63: Consultor SAP ECC (FI, CO, MM, SD, PP, QM, PM, WM) | B63: 0 | C63: 0 | D63: 0 | E63: 692.25
... A84: Tester | B84: 119.57 | C84: 170.55 | D84: 230 | E84: 310
B93: PP | C93: 0 a 200 horas | G93: Papel | H93: H/h | I93: Horas/mês | J93: Mensal | K93: 12 meses
B94: P | C94: 201 a 300 horas | G94: Product Owner | H94: 192.88 | I94: 168 | J94: =H94*I94 -> 32403.84 | K94: =J94*12 -> 388846.08
B95: M | C95: 301 a 1000 horas | G95: Salesforce Tech Lead | H95: 283.32 | I95: 168 | J95: =H95*I95 -> 47597.76 | K95: =J95*12 -> 571173.12
B96: G | C96: 1001 a 1500 horas | G96: Salesforce Developer | H96: 257.64 | I96: 168 | J96: =H96*I96 -> 43283.52 | K96: =J96*12 -> 519402.24
B97: GG | C97: acima de 1500 horas | G97: Salesforce Developer | H97: 257.64 | I97: 168 | J97: =H97*I97 -> 43283.52 | K97: =J97*12 -> 519402.24
G98: Salesforce Developer | H98: 257.64 | I98: 168 | J98: =H98*I98 -> 43283.52 | K98: =J98*12 -> 519402.24
G99: Analista de Teste | H99: 193.74 | I99: 168 | J99: =H99*I99 -> 32548.32 | K99: =J99*12 -> 390579.84
J100: =SUM(J94:J99) -> 242400.48 | K100: =SUM(K94:K99) -> 2908805.8
B101: 2 - até 1 dia
B102: 3 - até 2 dias
B103: 5 - até 3 dias | G103: Papel | H103: H/h | I103: Horas/mês | J103: Mensal | K103: 10 meses
B104: 8 - 4 a 5 dias (menor complexidade) | G104: Product Owner | H104: 192.88 | I104: 168 | J104: =H104*I104 -> 32403.84 | K104: =J104*10 -> 324038.4
B105: 13 - 5 a 6 dias(maior complexidade) | G105: Salesforce Developer | H105: 257.64 | I105: 168 | J105: =H105*I105 -> 43283.52 | K105: =J105*10 -> 432835.2
B106: 21 - 8 a 9 dias | G106: Salesforce Developer | H106: 257.64 | I106: 168 | J106: =H106*I106 -> 43283.52 | K106: =J106*10 -> 432835.2
G107: Salesforce Developer | H107: 257.64 | I107: 168 | J107: =H107*I107 -> 43283.52 | K107: =J107*10 -> 432835.2
G108: Salesforce Developer | H108: 257.64 | I108: 168 | J108: =H108*I108 -> 43283.52 | K108: =J108*10 -> 432835.2
B109: 81 do squad e fazendo analise | C109: por sprint | G109: Analista de Teste | H109: 193.74 | I109: 168 | J109: =H109*I109 -> 32548.32 | K109: =J109*10 -> 325483.2
J110: =SUM(J104:J109) -> 238086.24 | K110: =SUM(K104:K109) -> 2380862.4
B111: 21 Point por dev | C111: por sprint
B113: Temos uma média de 90 Story Point por Sprint

Sheet SIMULADO DESMOBILIZAÇAO
A1: INIBANK | B1: INICIATIVA | C1: Tipo | D1: Prestadora | E1: Matrícula | F1: Nome | H1: Projeção 2026 | I1: 46023 | J1: 46054 | K1: 46082 | L1: 46113 | M1: 46143 | N1: 46174 | O1: 46204 | P1: 46235 | Q1: 46266 | R1: 46296 | S1: 46327 | T1: 46357
A2: INIBANK-1173 | B2: [Book] Squad Salesforce (Atendimento) | C2: Forecast | H2: =SUM(I2:T2) -> 3955366 | I2: =329613.833333333 -> 329613.83 | J2: 329613.83 | K2: 329613.83 | L2: 329613.83 | M2: 329613.83 | N2: 329613.83 | O2: 329613.83 | P2: 329613.83 | Q2: 329613.83 | R2: 329613.83 | S2: 329613.83 | T2: 329613.83
A3: INIBANK-1173 | B3: [Book] Squad Salesforce (Atendimento) | C3: Realizado | H3: =SUM(I3:T3) -> 451723.18 | I3: 155501.04 | J3: 296222.14 | K3: 0 | L3: 0 | M3: 0 | N3: 0 | O3: 0 | P3: 0 | Q3: 0 | R3: 0 | S3: 0 | T3: 0
A5: INIBANK-1173 | B5: [Book] Squad Salesforce (Atendimento) | C5: Resultado | H5: =SUM(I5:T5) -> 3503642.8 | I5: =I2-I3 -> 174112.8 | J5: =J2-J3 -> 33391.689 | K5: =K2-K3 -> 329613.83 | L5: =L2-L3 -> 329613.83 | M5: =M2-M3 -> 329613.83 | N5: =N2-N3 -> 329613.83 | O5: =O2-O3 -> 329613.83 | P5: =P2-P3 -> 329613.83 | ... T5: =T2-T3 -> 329613.83
A7: INIBANK-1173 | B7: [Book] Squad Salesforce (Atendimento) | C7: Forecast Projetado | H7: =H5 -> 3503642.8 | K7: =$H$7/10 -> 350364.28 | L7: =$H$7/10 -> 350364.28 | M7: =$H$7/10 -> 350364.28 | N7: =$H$7/10 -> 350364.28 | O7: =$H$7/10 -> 350364.28 | P7: =$H$7/10 -> 350364.28 | Q7: =$H$7/10 -> 350364.28 | R7: =$H$7/10 -> 350364.28 | ... T7: =$H$7/10 -> 350364.28
K9: 22/02 - 21/03 | L9: 22/03 - 10/04
K10: =8*20 -> 160 | L10: =15*8 -> 120
K11: =8*20 -> 160 | L11: 130
A12: INIBANK-1173 | B12: [Book] Squad Salesforce (Atendimento) | C12: Time Alocado | D12: Sys4B | E12: P0660057 | F12: Cleiton Lima de Jesus | G12: 228.58 | H12: =SUM(I12:T12) -> 69945.48 | K12: =VLOOKUP($E12,'ORÇAMENTO 2026 v3'!$D:$X,10,0) -> 40230.08 | L12: =G12*$L$11 -> 29715.4
A13: INIBANK-1173 | B13: [Book] Squad Salesforce (Atendimento) | C13: Time Alocado | D13: Sys4B | E13: P0656797 | F13: Gustavo Seiji Onizuka | G13: 213.87 | H13: =SUM(I13:T13) -> 65444.22 | K13: =VLOOKUP($E13,'ORÇAMENTO 2026 v3'!$D:$X,10,0) -> 37641.12 | L13: =G13*$L$11 -> 27803.1
A14: INIBANK-1173 | B14: [Book] Squad Salesforce (Atendimento) | C14: Time Alocado | D14: Sys4B | E14: P0658519 | F14: Leonardo Lins | G14: 213.87 | H14: =SUM(I14:T14) -> 65444.22 | K14: =VLOOKUP($E14,'ORÇAMENTO 2026 v3'!$D:$X,10,0) -> 37641.12 | L14: =G14*$L$11 -> 27803.1
A15: INIBANK-1173 | B15: [Book] Squad Salesforce (Atendimento) | C15: Time Alocado | D15: Sys4B | E15: P0654694 | F15: Carlos Eduardo Santos Santana | G15: 213.87 | H15: =SUM(I15:T15) -> 65444.22 | K15: =VLOOKUP($E15,'ORÇAMENTO 2026 v3'!$D:$X,10,0) -> 37641.12 | L15: =G15*$L$11 -> 27803.1
A16: INIBANK-1173 | B16: [Book] Squad Salesforce (Atendimento) | C16: Time Alocado | D16: Capgemini | E16: P0661574 | F16: Leonardo Lassance | G16: 299.76 | H16: =SUM(I16:T16) -> 91726.56 | K16: =VLOOKUP($E16,'ORÇAMENTO 2026 v3'!$D:$X,10,0) -> 52757.76 | L16: =G16*$L$11 -> 38968.8
A17: INIBANK-1173 | B17: [Book] Squad Salesforce (Atendimento) | C17: Time Alocado | D17: Capgemini | E17: P0661361 | F17: Fernando da Silva Trevisan | G17: 289.35 | H17: =SUM(I17:T17) -> 88541.1 | K17: =VLOOKUP($E17,'ORÇAMENTO 2026 v3'!$D:$X,10,0) -> 50925.6 | L17: =G17*$L$11 -> 37615.5
A18: INIBANK-1173 | B18: [Book] Squad Salesforce (Atendimento) | C18: Time Alocado | D18: Capgemini | E18: P0661715 | F18: Marcel Vallim Moreira | G18: 202.62 | H18: =SUM(I18:T18) -> 62001.72 | K18: =VLOOKUP($E18,'ORÇAMENTO 2026 v3'!$D:$X,10,0) -> 35661.12 | L18: =G18*$L$11 -> 26340.6
A19: INIBANK-1173 | B19: [Book] Squad Salesforce (Atendimento) | C19: Time Alocado | D19: Capgemini | E19: P0661738 | F19: Erick Delfino Silva | G19: 193.74 | H19: =SUM(I19:T19) -> 59284.44 | K19: =VLOOKUP($E19,'ORÇAMENTO 2026 v3'!$D:$X,10,0) -> 34098.24 | L19: =G19*$L$11 -> 25186.2
A22: INIBANK-1173 | B22: [Book] Squad Salesforce (Atendimento) | C22: Corte Orçamento | H22: 2400000 | M22: =$H$22/8 -> 300000 | N22: =$H$22/8 -> 300000 | O22: =$H$22/8 -> 300000 | P22: =$H$22/8 -> 300000 | Q22: =$H$22/8 -> 300000 | R22: =$H$22/8 -> 300000 | S22: =$H$22/8 -> 300000 | T22: =$H$22/8 -> 300000
A24: INIBANK-1173 | B24: [Book] Squad Salesforce (Atendimento) | C24: Forecast Reajustado | H24: =SUM(I24:T24) -> 535810.86 | I24: =I7-I22 -> 0 | J24: =J7-J22 -> 0 | K24: =K7-SUM(K12:K19)-K22 -> 23768.122 | L24: =L7-SUM(L12:L19)-L22 -> 109128.48 | M24: =M7-SUM(M12:M19)-M22 -> 50364.282 | N24: =N7-SUM(N12:N19)-N22 -> 50364.282 | O24: =O7-SUM(O12:O19)-O22 -> 50364.282 | P24: =P7-SUM(P12:P19)-P22 -> 50364.282 | Q24: =Q7-SUM(Q12:Q19)-Q22 -> 50364.282 | R24: =R7-SUM(R12:R19)-R22 -> 50364.282 | ... T24: =T7-SUM(T12:T19)-T22 -> 50364.282
A25: INIBANK-1173 | B25: [Book] Squad Salesforce (Atendimento) | C25: Forecast Projetado | H25: =H24 -> 535810.86 | M25: =$H$25/7 -> 76544.409 | N25: =$H$25/7 -> 76544.409 | O25: =$H$25/7 -> 76544.409 | P25: =$H$25/7 -> 76544.409 | Q25: =$H$25/7 -> 76544.409 | R25: =$H$25/7 -> 76544.409 | S25: =$H$25/7 -> 76544.409 | T25: 0
A27: INIBANK-1173 | B27: [Book] Squad Salesforce (Atendimento) | C27: Time Alocado Reajustado | D27: Sys4B | E27: P0660057 | F27: Cleiton Lima de Jesus | G27: 228.58 | H27: =SUM(I27:T27) -> 281610.56 | M27: =$G27*176 -> 40230.08 | N27: =$G27*176 -> 40230.08 | O27: =$G27*176 -> 40230.08 | P27: =$G27*176 -> 40230.08 | Q27: =$G27*176 -> 40230.08 | R27: =$G27*176 -> 40230.08 | S27: =$G27*176 -> 40230.08
A28: INIBANK-1173 | B28: [Book] Squad Salesforce (Atendimento) | C28: Time Alocado Reajustado | D28: Sys4B | E28: P0658519 | F28: Leonardo Lins | G28: 213.87 | H28: =SUM(I28:T28) -> 263487.84 | M28: =$G28*176 -> 37641.12 | N28: =$G28*176 -> 37641.12 | O28: =$G28*176 -> 37641.12 | P28: =$G28*176 -> 37641.12 | Q28: =$G28*176 -> 37641.12 | R28: =$G28*176 -> 37641.12 | S28: =$G28*176 -> 37641.12

Sheet ORÇAMENTO 2026 v3
A1: Nome Prestador | B1: e-mail Porto | C1: e-mail Consultoria | D1: Matrícula | E1: Papel | F1: Consultoria | G1: Iniciativa | H1: Time | I1: R$ H/h | J1: Estimado Mensal | K1: 46023 | L1: 46054 | M1: 46082 | N1: 46113 | O1: 46143 | P1: 46174 | Q1: 46204 | R1: 46235 | S1: 46266 | T1: 46296 | U1: 46327 | V1: 46357 | W1: Estimado até Dez/25 | X1: Estimado 11 meses
A3: Leonardo Lassance | B3: leonardo.lassance@portoseguro.com.br | C3: leonardo.lassance@capgemini.com | D3: P0661574 | E3: Project Manager | F3: Capgemini | G3: INIBANK-1173 | H3: Evoluções e Melhorias | I3: 299.76 | J3: =I3*176 -> 52757.76 | K3: =$J3 -> 52757.76 | L3: =$J3 -> 52757.76 | M3: =$J3 -> 52757.76 | N3: =$J3 -> 52757.76 | O3: =$J3 -> 52757.76 | P3: =$J3 -> 52757.76 | Q3: =$J3 -> 52757.76 | R3: =$J3 -> 52757.76 | ... V3: =$J3 -> 52757.76 | W3: =SUM(K3:V3) -> 633093.12 | X3: =J3*11 -> 580335.36
A4: Fernando da Silva Trevisan | B4: fernando.trevisan@portoseguro.com.br | C4: fernando.trevisan@capgemini.com | D4: P0661361 | E4: Tech Lead Salesforce | F4: Capgemini | G4: INIBANK-1173 | H4: Evoluções e Melhorias | I4: 289.35 | J4: =I4*176 -> 50925.6 | K4: =$J4 -> 50925.6 | L4: =$J4 -> 50925.6 | M4: =$J4 -> 50925.6 | N4: =$J4 -> 50925.6 | O4: =$J4 -> 50925.6 | P4: =$J4 -> 50925.6 | Q4: =$J4 -> 50925.6 | R4: =$J4 -> 50925.6 | ... V4: =$J4 -> 50925.6 | W4: =SUM(K4:V4) -> 611107.2 | X4: =J4*11 -> 560181.6
A5: Cleiton Lima de Jesus | B5: cleiton.jesus@portoseguro.com.br | C5: cleiton.jesus@sys4b.com.br | D5: P0660057 | E5: Desenvolvedor Salesforce | F5: Sys4B | G5: INIBANK-1173 | H5: Evoluções e Melhorias | I5: 228.58 | J5: =I5*176 -> 40230.08 | K5: =$J5 -> 40230.08 | L5: =$J5 -> 40230.08 | M5: =$J5 -> 40230.08 | N5: =$J5 -> 40230.08 | O5: =$J5 -> 40230.08 | P5: =$J5 -> 40230.08 | Q5: =$J5 -> 40230.08 | R5: =$J5 -> 40230.08 | ... V5: =$J5 -> 40230.08 | W5: =SUM(K5:V5) -> 482760.96 | X5: =J5*11 -> 442530.88
A6: Gustavo Seiji Onizuka | B6: gustavo.onizuka@portoseguro.com.br | C6: gustavo.s.onizuka@sys4b.com.br | D6: P0656797 | E6: Desenvolvedor Salesforce | F6: Sys4B | G6: INIBANK-1173 | H6: Evoluções e Melhorias | I6: 213.87 | J6: =I6*176 -> 37641.12 | K6: =$J6 -> 37641.12 | L6: =$J6 -> 37641.12 | M6: =$J6 -> 37641.12 | N6: =$J6 -> 37641.12 | O6: =$J6 -> 37641.12 | P6: =$J6 -> 37641.12 | Q6: =$J6 -> 37641.12 | R6: =$J6 -> 37641.12 | ... V6: =$J6 -> 37641.12 | W6: =SUM(K6:V6) -> 451693.44 | X6: =J6*11 -> 414052.32
A7: Leonardo Lins | B7: leonardo.lins@portoseguro.com.br | C7: leonardo.silva@sys4b.com.br | D7: P0658519 | E7: Desenvolvedor Salesforce | F7: Sys4B | G7: INIBANK-1173 | H7: Evoluções e Melhorias | I7: 213.87 | J7: =I7*176 -> 37641.12 | K7: =$J7 -> 37641.12 | L7: =$J7 -> 37641.12 | M7: =$J7 -> 37641.12 | N7: =$J7 -> 37641.12 | O7: =$J7 -> 37641.12 | P7: =$J7 -> 37641.12 | Q7: =$J7 -> 37641.12 | R7: =$J7 -> 37641.12 | ... V7: =$J7 -> 37641.12 | W7: =SUM(K7:V7) -> 451693.44 | X7: =J7*11 -> 414052.32
A8: Marcel Vallim Moreira | B8: marcel.moreira@portoseguro.com.br | C8: marcel.moreira@capgemini.com | D8: P0661715 | E8: Desenvolvedor Salesforce | F8: Capgemini | G8: INIBANK-1173 | H8: Evoluções e Melhorias | I8: 202.62 | J8: =I8*176 -> 35661.12 | K8: =$J8 -> 35661.12 | L8: =$J8 -> 35661.12 | M8: =$J8 -> 35661.12 | N8: =$J8 -> 35661.12 | O8: =$J8 -> 35661.12 | P8: =$J8 -> 35661.12 | Q8: =$J8 -> 35661.12 | R8: =$J8 -> 35661.12 | ... V8: =$J8 -> 35661.12 | W8: =SUM(K8:V8) -> 427933.44 | X8: =J8*11 -> 392272.32
A9: Carlos Eduardo Santos Santana | B9: carloseduardo.santos@portoseguro.com.br | C9: carlos.santana@sys4b.com.br | D9: P0654694 | E9: Desenvolvedor Salesforce | F9: Sys4B | G9: INIBANK-1173 | H9: Evoluções e Melhorias | I9: 213.87 | J9: =I9*176 -> 37641.12 | K9: =$J9 -> 37641.12 | L9: =$J9 -> 37641.12 | M9: =$J9 -> 37641.12 | N9: =$J9 -> 37641.12 | O9: =$J9 -> 37641.12 | P9: =$J9 -> 37641.12 | Q9: =$J9 -> 37641.12 | R9: =$J9 -> 37641.12 | ... V9: =$J9 -> 37641.12 | W9: =SUM(K9:V9) -> 451693.44 | X9: =J9*11 -> 414052.32
A10: Erick Delfino Silva | B10: erick.delfino@portoseguro.com.br | C10: erick.silva@capgemini.com | D10: P0661738 | E10: Analista de Teste | F10: Capgemini | G10: INIBANK-1173 | H10: Evoluções e Melhorias | I10: 193.74 | J10: =I10*176 -> 34098.24 | K10: =$J10 -> 34098.24 | L10: =$J10 -> 34098.24 | M10: =$J10 -> 34098.24 | N10: =$J10 -> 34098.24 | O10: =$J10 -> 34098.24 | P10: =$J10 -> 34098.24 | Q10: =$J10 -> 34098.24 | R10: =$J10 -> 34098.24 | ... V10: =$J10 -> 34098.24 | W10: =SUM(K10:V10) -> 409178.88 | X10: =J10*11 -> 375080.64
J11: =SUM(J3:J10) -> 326596.16 | K11: =SUM(K3:K10) -> 326596.16 | L11: =SUM(L3:L10) -> 326596.16 | M11: =SUM(M3:M10) -> 326596.16 | N11: =SUM(N3:N10) -> 326596.16 | O11: =SUM(O3:O10) -> 326596.16 | P11: =SUM(P3:P10) -> 326596.16 | Q11: =SUM(Q3:Q10) -> 326596.16 | ... X11: =SUM(X3:X10) -> 3592557.8
A14: Francielle Thiezo Revesso Pinto | B14: francielle.pinto@portoseguro.com.br | C14: francielle.revesso@sys4b.com.br | D14: P0662312 | E14: Administrador Salesforce | F14: Sys4B | G14: INIBANK-289 | H14: Plataforma Salesforce Odin | I14: 213.87 | J14: =I14*176 -> 37641.12 | K14: =$J14 -> 37641.12 | L14: =$J14 -> 37641.12 | M14: =$J14 -> 37641.12 | N14: =$J14 -> 37641.12 | O14: =$J14 -> 37641.12 | P14: =$J14 -> 37641.12 | Q14: =$J14 -> 37641.12 | R14: =$J14 -> 37641.12 | ... V14: =$J14 -> 37641.12 | W14: =SUM(K14:V14) -> 451693.44 | X14: =J14*11 -> 414052.32
A15: Lucas Takita | B15: lucas.takita@portoseguro.com.br | C15: lucas.takita@infinitysys.com.br | D15: P0650648 | E15: Desenvolvedor Salesforce Sênior | F15: Sys4B | G15: INIBANK-289 | H15: Plataforma Salesforce Odin | I15: 213.87 | J15: =I15*176 -> 37641.12 | K15: =$J15 -> 37641.12 | L15: =$J15 -> 37641.12 | M15: =$J15 -> 37641.12 | N15: =$J15 -> 37641.12 | O15: =$J15 -> 37641.12 | P15: =$J15 -> 37641.12 | Q15: =$J15 -> 37641.12 | R15: =$J15 -> 37641.12 | ... V15: =$J15 -> 37641.12 | W15: =SUM(K15:V15) -> 451693.44 | X15: =J15*11 -> 414052.32
A16: Gabriel Costa Datovo Inoue Maekawa | B16: gabriel.maekawa@portoseguro.com.br | C16: gabriel.montalbini@sys4b.com.br | D16: P0663654 | E16: Desenvolvedor Pleno | F16: Sys4B | G16: INIBANK-289 | H16: Plataforma Salesforce Odin | I16: 191.36 | J16: =I16*176 -> 33679.36 | K16: =$J16 -> 33679.36 | L16: =$J16 -> 33679.36 | M16: =$J16 -> 33679.36 | N16: =$J16 -> 33679.36 | O16: =$J16 -> 33679.36 | P16: =$J16 -> 33679.36 | Q16: =$J16 -> 33679.36 | R16: =$J16 -> 33679.36 | ... V16: =$J16 -> 33679.36 | W16: =SUM(K16:V16) -> 404152.32 | X16: =J16*11 -> 370472.96
A17: Plantão Salesforce Odin + OverTime | D17: P0000000 | E17: Desenvolvedor Salesforce Sênior | F17: Sys4B | G17: INIBANK-289 | H17: Plataforma Salesforce Odin | I17: 213.87 | J17: 40000 | K17: =$J17 -> 40000 | L17: =$J17 -> 40000 | M17: =$J17 -> 40000 | N17: =$J17 -> 40000 | O17: =$J17 -> 40000 | P17: =$J17 -> 40000 | Q17: =$J17 -> 40000 | R17: =$J17 -> 40000 | ... V17: =$J17 -> 40000 | W17: =SUM(K17:V17) -> 480000 | X17: =J17*11 -> 440000
J18: =SUM(J14:J17) -> 148961.6 | K18: =SUM(K14:K17) -> 148961.6 | L18: =SUM(L14:L17) -> 148961.6 | M18: =SUM(M14:M17) -> 148961.6 | N18: =SUM(N14:N17) -> 148961.6 | O18: =SUM(O14:O17) -> 148961.6 | P18: =SUM(P14:P17) -> 148961.6 | Q18: =SUM(Q14:Q17) -> 148961.6 | ... X18: =SUM(X14:X17) -> 1638577.6

Sheet ORÇAMENTO 2026 v4
A1: Nome Prestador | B1: e-mail Porto | C1: e-mail Consultoria | D1: Matrícula | E1: Papel | F1: Consultoria | G1: Iniciativa | H1: Time | I1: R$ H/h | J1: Estimado Mensal | K1: 46023 | L1: 46054 | M1: 46082 | N1: 46113 | O1: 46143 | P1: 46174 | Q1: 46204 | R1: 46235 | S1: 46266 | T1: 46296 | U1: 46327 | V1: 46357 | W1: Estimado até Dez/25 | X1: Estimado 11 meses
A2: Fernando da Silva Trevisan | B2: fernando.trevisan@portoseguro.com.br | C2: fernando.trevisan@capgemini.com | D2: P0661361 | E2: Tech Lead Salesforce | F2: Capgemini | G2: INIBANK-1173 | H2: Evoluções e Melhorias | I2: 289.35 | J2: =I2*176 -> 50925.6 | K2: =$J2 -> 50925.6 | L2: =$J2 -> 50925.6 | M2: =$J2 -> 50925.6 | N2: =$J2 -> 50925.6 | O2: =$J2 -> 50925.6 | P2: =$J2 -> 50925.6 | Q2: =$J2 -> 50925.6 | R2: =$J2 -> 50925.6 | ... V2: =$J2 -> 50925.6 | W2: =SUM(K2:V2) -> 611107.2 | X2: =J2*11 -> 560181.6
A3: Cleiton Lima de Jesus | B3: cleiton.jesus@portoseguro.com.br | C3: cleiton.jesus@sys4b.com.br | D3: P0660057 | E3: Desenvolvedor Salesforce | F3: Sys4B | G3: INIBANK-1173 | H3: Evoluções e Melhorias | I3: 228.58 | J3: =I3*176 -> 40230.08 | K3: =$J3 -> 40230.08 | L3: =$J3 -> 40230.08 | M3: =$J3 -> 40230.08 | N3: =$J3 -> 40230.08 | O3: =$J3 -> 40230.08 | P3: =$J3 -> 40230.08 | Q3: =$J3 -> 40230.08 | R3: =$J3 -> 40230.08 | ... V3: =$J3 -> 40230.08 | W3: =SUM(K3:V3) -> 482760.96 | X3: =J3*11 -> 442530.88
J6: =SUM(J2:J19) -> #REF! | K6: =SUM(K2:K19) -> #REF! | L6: =SUM(L2:L19) -> #REF! | M6: =SUM(M2:M19) -> #REF! | N6: =SUM(N2:N19) -> #REF! | O6: =SUM(O2:O19) -> #REF! | P6: =SUM(P2:P19) -> #REF! | Q6: =SUM(Q2:Q19) -> #REF! | ... X6: =SUM(X2:X19) -> #REF!
A9: Francielle Thiezo Revesso Pinto | B9: francielle.pinto@portoseguro.com.br | C9: francielle.revesso@sys4b.com.br | D9: P0662312 | E9: Administrador Salesforce | F9: Sys4B | G9: INIBANK-289 | H9: Plataforma Salesforce Odin | I9: 213.87 | J9: =I9*176 -> 37641.12 | K9: =$J9 -> 37641.12 | L9: =$J9 -> 37641.12 | M9: =$J9 -> 37641.12 | N9: =$J9 -> 37641.12 | O9: =$J9 -> 37641.12 | W9: =SUM(K9:V9) -> 188205.6 | X9: =J9*11 -> 414052.32
A10: Lucas Takita | B10: lucas.takita@portoseguro.com.br | C10: lucas.takita@infinitysys.com.br | D10: P0650648 | E10: Desenvolvedor Salesforce Sênior | F10: Sys4B | G10: INIBANK-289 | H10: Plataforma Salesforce Odin | I10: 213.87 | J10: =I10*176 -> 37641.12 | K10: =$J10 -> 37641.12 | L10: =$J10 -> 37641.12 | M10: =$J10 -> 37641.12 | N10: =$J10 -> 37641.12 | O10: =$J10 -> 37641.12 | P10: =$J10 -> 37641.12 | Q10: =$J10 -> 37641.12 | R10: =$J10 -> 37641.12 | ... V10: =$J10 -> 37641.12 | W10: =SUM(K10:V10) -> 451693.44 | X10: =J10*11 -> 414052.32
A11: Gabriel Costa Datovo Inoue Maekawa | B11: gabriel.maekawa@portoseguro.com.br | C11: gabriel.montalbini@sys4b.com.br | D11: P0663654 | E11: Desenvolvedor Pleno | F11: Sys4B | G11: INIBANK-289 | H11: Plataforma Salesforce Odin | I11: 191.36 | J11: =I11*176 -> 33679.36 | K11: =$J11 -> 33679.36 | L11: =$J11 -> 33679.36 | M11: =$J11 -> 33679.36 | N11: =$J11 -> 33679.36 | O11: =$J11 -> 33679.36 | P11: =$J11 -> 33679.36 | Q11: =$J11 -> 33679.36 | R11: =$J11 -> 33679.36 | ... V11: =$J11 -> 33679.36 | W11: =SUM(K11:V11) -> 404152.32 | X11: =J11*11 -> 370472.96
A12: Plantão Salesforce Odin + OverTime | D12: P0000000 | E12: Desenvolvedor Salesforce Sênior | F12: Sys4B | G12: INIBANK-289 | H12: Plataforma Salesforce Odin | I12: 213.87 | J12: 40000 | K12: =$J12 -> 40000 | L12: =$J12 -> 40000 | M12: =$J12 -> 40000 | N12: =$J12 -> 40000 | O12: =$J12 -> 40000 | P12: =$J12 -> 40000 | Q12: =$J12 -> 40000 | R12: =$J12 -> 40000 | ... V12: =$J12 -> 40000 | W12: =SUM(K12:V12) -> 480000 | X12: =J12*11 -> 440000
J13: =SUM(J9:J12) -> 148961.6 | K13: =SUM(K9:K12) -> 148961.6 | L13: =SUM(L9:L12) -> 148961.6 | M13: =SUM(M9:M12) -> 148961.6 | N13: =SUM(N9:N12) -> 148961.6 | O13: =SUM(O9:O12) -> 148961.6 | P13: =SUM(P9:P12) -> 111320.48 | Q13: =SUM(Q9:Q12) -> 111320.48 | ... X13: =SUM(X9:X12) -> 1638577.6
A18: Leonardo Lassance | B18: leonardo.lassance@portoseguro.com.br | C18: leonardo.lassance@capgemini.com | D18: P0661574 | E18: Project Manager | F18: Capgemini | G18: INIBANK-1173 | H18: Evoluções e Melhorias | I18: 299.76 | J18: =I18*176 -> 52757.76 | K18: =$J18 -> 52757.76 | L18: =$J18 -> 52757.76 | M18: =$J18 -> 52757.76 | N18: =$J18 -> 52757.76 | O18: =$J18 -> 52757.76 | P18: =$J18 -> 52757.76 | Q18: =$J18 -> 52757.76 | R18: =$J18 -> 52757.76 | ... V18: =$J18 -> 52757.76 | W18: =SUM(K18:V18) -> 633093.12
A19: Erick Delfino Silva | B19: erick.delfino@portoseguro.com.br | C19: erick.silva@capgemini.com | D19: P0661738 | E19: Analista de Teste | F19: Capgemini | G19: INIBANK-1173 | H19: Evoluções e Melhorias | I19: 193.74 | J19: =I19*176 -> 34098.24 | K19: =$J19 -> 34098.24 | L19: =$J19 -> 34098.24 | M19: =$J19 -> 34098.24 | N19: =$J19 -> 34098.24 | O19: =$J19 -> 34098.24 | P19: =$J19 -> 34098.24 | Q19: =$J19 -> 34098.24 | R19: =$J19 -> 34098.24 | ... V19: =$J19 -> 34098.24 | W19: =SUM(K19:V19) -> 409178.88
A20: Leonardo Lins | B20: leonardo.lins@portoseguro.com.br | C20: leonardo.silva@sys4b.com.br | D20: P0658519 | E20: Desenvolvedor Salesforce | F20: Sys4B | G20: INIBANK-1173 | H20: Evoluções e Melhorias | I20: 213.87 | J20: =I20*176 -> 37641.12 | K20: =$J20 -> 37641.12 | L20: =$J20 -> 37641.12 | M20: =$J20 -> 37641.12 | N20: =$J20 -> 37641.12 | O20: =$J20 -> 37641.12 | P20: =$J20 -> 37641.12 | Q20: =$J20 -> 37641.12 | R20: =$J20 -> 37641.12 | ... V20: =$J20 -> 37641.12 | W20: =SUM(K20:V20) -> 451693.44
A21: Marcel Vallim Moreira | B21: marcel.moreira@portoseguro.com.br | C21: marcel.moreira@capgemini.com | D21: P0661715 | E21: Desenvolvedor Salesforce | F21: Capgemini | G21: INIBANK-1173 | H21: Evoluções e Melhorias | I21: 202.62 | J21: =I21*176 -> 35661.12 | K21: =$J21 -> 35661.12 | L21: =$J21 -> 35661.12 | M21: =$J21 -> 35661.12 | N21: =$J21 -> 35661.12 | O21: =$J21 -> 35661.12 | P21: =$J21 -> 35661.12 | Q21: =$J21 -> 35661.12 | R21: =$J21 -> 35661.12 | ... V21: =$J21 -> 35661.12 | W21: =SUM(K21:V21) -> 427933.44
A22: Gustavo Seiji Onizuka | B22: gustavo.onizuka@portoseguro.com.br | C22: gustavo.s.onizuka@sys4b.com.br | D22: P0656797 | E22: Desenvolvedor Salesforce | F22: Sys4B | G22: INIBANK-1173 | H22: Evoluções e Melhorias | I22: 213.87 | J22: =I22*176 -> 37641.12 | K22: =$J22 -> 37641.12 | L22: =$J22 -> 37641.12 | M22: =$J22 -> 37641.12 | N22: =$J22 -> 37641.12 | O22: =$J22 -> 37641.12 | P22: =$J22 -> 37641.12 | Q22: =$J22 -> 37641.12 | R22: =$J22 -> 37641.12 | ... V22: =$J22 -> 37641.12 | W22: =SUM(K22:V22) -> 451693.44
A23: Carlos Eduardo Santos Santana | B23: carloseduardo.santos@portoseguro.com.br | C23: carlos.santana@sys4b.com.br | D23: P0654694 | E23: Desenvolvedor Salesforce | F23: Sys4B | G23: INIBANK-1173 | H23: Evoluções e Melhorias | I23: 213.87 | J23: =I23*176 -> 37641.12 | K23: =$J23 -> 37641.12 | L23: =$J23 -> 37641.12 | M23: =$J23 -> 37641.12 | N23: =$J23 -> 37641.12 | O23: =$J23 -> 37641.12 | P23: =$J23 -> 37641.12 | Q23: =$J23 -> 37641.12 | R23: =$J23 -> 37641.12 | ... V23: =$J23 -> 37641.12 | W23: =SUM(K23:V23) -> 451693.44
N24: =SUM(N18:N23) -> 235440.48 | O24: =SUM(O18:O23) -> 235440.48 | P24: =SUM(P18:P23) -> 235440.48 | Q24: =SUM(Q18:Q23) -> 235440.48 | R24: =SUM(R18:R23) -> 235440.48 | S24: =SUM(S18:S23) -> 235440.48 | T24: =SUM(T18:T23) -> 235440.48 | U24: =SUM(U18:U23) -> 235440.48 | V24: =SUM(V18:V23) -> 235440.48 | W24: =SUM(N24:V24) -> 2118964.3

Sheet Forecast - Iniciativas
A1: DCheck | B1: STATUS | C1: INIBANK | D1: INICIATIVA | E1: Time | F1: CNPJ DE FATURAMENTO | G1: Orçamento Aprovado | H1: jan | I1: fev | J1: mar | K1: abr | L1: mai | M1: Total Realizado | N1: Forecast Jun/Dez | O1: jan | P1: fev | Q1: mar | R1: abr | S1: mai | T1: jun | U1: jul | V1: ago | W1: set | X1: out | Y1: nov | Z1: dez | AA1: Racional utilizado para a projeção | AB1: Domínio | AC1: Produto | AD1: Coord Tech | AE1: Super/Ger Tech | AF1: Diretoria | AG1: Memória de calculo. | AH1: Observação
A2: Encerrado | B2: OK | C2: INIBANK-054 | D2: INIBANK-054 - Evoluções Salesforce para o Cartão | G2: 747658 | H2: 33711.57 | I2: 205881.24 | J2: -50622.33 | K2: 217341.29 | L2: 421516.21 | M2: 827827.98 | N2: 0 | O2: 249219 | P2: 249219 | Q2: 249219 | R2: 249219 | S2: 0 | T2: 0 | U2: 0 | V2: 0 | W2: 0 | X2: 0 | Y2: 0 | Z2: 0 | AB2: Atendimento | AC2: Cartão de Crédito | AD2: Marcos Rosa | AE2: Anderson Ami | AF2: Tiago Violin
A3: Encerrado | B3: OK | C3: INIBANK-226 | D3: INIBANK-226 - Integração Consórcio (Newcon com Salesforce) | G3: 1300000 | H3: 411498.32 | K3: 22845.74 | L3: 311809.5 | M3: 746153.56 | N3: 0 | O3: 260000 | P3: 260000 | Q3: 260000 | R3: 260000 | S3: 260000 | T3: 0 | U3: 0 | V3: 0 | W3: 0 | X3: 0 | Y3: 0 | Z3: 0 | AB3: Atendimento | AC3: Consórcio | AD3: Marcos Rosa | AE3: Anderson Ami | AF3: Tiago Violin
B4: OK | C4: INIBANK-1053 | D4: SALESFORCE MELHORIAS | E4: Evoluções e Melhorias | N4: =SUM(T4:Z4) -> 1830090 | T4: 0 | U4: 305015 | V4: 305015 | W4: 305015 | X4: 305015 | Y4: 305015 | Z4: 305015 | AD4: Marcos Rosa | AE4: Anderson Ami | AF4: Tiago Violin
A5: Em execução | B5: OK | C5: INIBANK-289 | D5: Sustentação Atendimento Salesforce Odin | E5: Plataforma Salesforce Odin | F5: PortoSeg 04.862.600/0001-10 | G5: 1378600 | I5: 24328.92 | J5: 21372 | K5: 165788.04 | L5: 262365.65 | M5: 473854.61 | N5: 904745.03 | P5: -24328.92 | Q5: -21372 | R5: -165788.04 | S5: -262365.65 | T5: 129249.29 | U5: 129249.29 | V5: 129249.29 | W5: 129249.29 | X5: 129249.29 | Y5: 129249.29 | Z5: 129249.29 | AB5: Atendimento | AC5: Atendimento | AD5: Marcos Rosa | AE5: Anderson Ami | AF5: Luciana Hildebrandi | AG5: Somente para o time de Atendimento
B6: OK | C6: INIBANK-611 | D6: Implantação do SalesForce para Central de Atendimento de Clientes PJ | E6: Novos Projetos | F6: PortoSeg 04.862.600/0001-10 | G6: 5680000 | H6: 62326.64 | I6: 56072.52 | J6: 77746.08 | K6: 41801.39 | L6: 380933.63 | M6: 618880.26 | N6: 2722650 | O6: -386950 | P6: -386950 | Q6: -386950 | R6: -386950 | S6: -386950 | T6: 388950 | U6: 388950 | V6: 388950 | W6: 388950 | X6: 388950 | Y6: 388950 | Z6: 388950 | AB6: Atendimento | AC6: Cartão de Crédito PJ | AD6: Marcos Rosa | AE6: Anderson Ami | AF6: Tiago Violin
A7: Ajustar Forecast | B7: OK | C7: INIBANK-906 | D7: [Salesforce] - Segurança (autenticação) | E7: Evoluções e Melhorias | F7: PortoSeg 04.862.600/0001-10 | G7: 74500 | N7: 100000 | T7: 25000 | U7: 25000 | V7: 25000 | W7: 25000 | X7: 0 | Y7: 0 | Z7: 0 | AB7: Atendimento | AC7: Atendimento | AD7: Marcos Rosa | AE7: Anderson Ami | AF7: Tiago Violin
A8: Ajustar Forecast | B8: OK | C8: INIBANK-907 | D8: [Salesforce] - Adequação processos de atendimento no Pix da Conta | E8: Evoluções e Melhorias | F8: PortoSeg 04.862.600/0001-10 | G8: 74500 | J8: 30612.8 | K8: 15991.68 | L8: 29358.91 | N8: 100000 | T8: 25000 | U8: 25000 | V8: 25000 | W8: 25000 | X8: 0 | Y8: 0 | Z8: 0 | AB8: Atendimento | AC8: Atendimento | AD8: Marcos Rosa | AE8: Anderson Ami | AF8: Tiago Violin
B9: OK | C9: INIBANK-1173 | D9: Salesforce Evoluções e Melhorias Conta Digital e Cartão de Crédito | E9: Evoluções e Melhorias | F9: PortoSeg 04.862.600/0001-10 | N9: 1630090 | T9: =T4-(T7+T8) -> -50000 | U9: =U4-(U7+U8) -> 255015 | V9: =V4-(V7+V8) -> 255015 | W9: =W4-(W7+W8) -> 255015 | X9: =X4-(X7+X8) -> 305015 | Y9: =Y4-(Y7+Y8) -> 305015 | Z9: =Z4-(Z7+Z8) -> 305015 | AD9: Marcos Rosa | AE9: Anderson Ami | AF9: Tiago Violin
N10: =N7+N8+N9 -> 1830090
F16: Postergação de NF 2025/2026 | G16: Projeção 2026
C17: INIBANK-1173 | D17: [Book] Squad Salesforce (Atendimento) | F17: 196499 | G17: 3955366
C18: INIBANK-1417 | D18: [Sustentação] Atendimento / Salesforce | G18: 1865718

Sheet APROVAÇÕES E CONTROLE
A1: Prestador | B1: Frente | C1: Período de Apuração | D1: Aprovação das Horas | E1: NFe | F1: Data Emissão | G1: Valor Total | H1: Data Prev Vencimento | I1: Iniciativa | J1: Produto | K1: Descrição do Serv Prestado | L1: Aprovação do Pgto | M1: Data Real Pgto | N1: Status Pgto | O1: Observação
A2: Sys4B | B2: Atendimento | C2: 22/12/24 a 21/01/25 | D2: Sim | E2: 2701 | F2: 45699 | G2: 191611.98 | H2: 45759 | I2: INIBANK-54 Evoluções Salesforce para o Cartão e INIBANK-225 Evoluções Salesforce para a Conta Digital | J2: Cartão de Crédito Pessoa Física e Conta Digital PF | K2: Desenvolvimento no ambiente Salesforce Odin para melhorias de jornadas de atendimento para Cartão de Crédito Pessoa Física e Conta Digital PF | L2: Sim | N2: Em aberto | O2: Não há memória de cálculo pois passou a valer apenas em meses posteriores
A3: Sys4B | B3: Atendimento | C3: 22/12/24 a 21/01/25 | D3: Sim | E3: 2702 | F3: 45699 | G3: 24607.42 | H3: 45759 | I3: INIBANK-54 Evoluções Salesforce para o Cartão e INIBANK-225 Evoluções Salesforce para a Conta Digital | J3: Cartão de Crédito Pessoa Física e Conta Digital PF | K3: Desenvolvimento no ambiente Salesforce Odin para melhorias de jornadas de atendimento para Cartão de Crédito Pessoa Física e Conta Digital PF | L3: Sim | N3: Em aberto | O3: Não há memória de cálculo pois passou a valer apenas em meses posteriores. Aprovado o pgto dia 16/06/25 via e-mail - PORTO BANK - Notas Fiscais Pendentes - Abril/25
A4: Sys4B | B4: Atendimento | C4: 22/01/25 a 21/02/25 | D4: Sim | E4: 2753 | F4: 45727 | G4: 303490.65 | H4: 45787 | I4: INIBANK-54 Evoluções Salesforce para o Cartão e INIBANK-225 Evoluções Salesforce para a Conta Digital | J4: Cartão de Crédito Pessoa Física e Conta Digital PF | K4: Desenvolvimento no ambiente Salesforce Odin para melhorias de jornadas de atendimento para Cartão de Crédito Pessoa Física e Conta Digital PF | L4: Sim | N4: Em aberto | O4: Não há memória de cálculo pois passou a valer apenas em meses posteriores
A5: Sys4B | B5: Atendimento | C5: 22/02/25 a 21/03/25 | D5: Sim | E5: 2791 | F5: 45749 | G5: 212597.4 | H5: 45809 | I5: INIBANK-54 Evoluções Salesforce para o Cartão e INIBANK-225 Evoluções Salesforce para a Conta Digital | J5: Cartão de Crédito Pessoa Física e Conta Digital PF | K5: Desenvolvimento no ambiente Salesforce Odin para melhorias de jornadas de atendimento para Cartão de Crédito Pessoa Física e Conta Digital PF | L5: Sim | N5: Em aberto | O5: Houve um desconto sobre o valor total. Aprovado para pgto dia 13/06/25 via e-mail - Fwd: PORTO SEGURO - NF 2791 - SYS4B
A6: Sys4B | B6: Sinistro Auto | C6: 22/02/25 a 21/03/25 | E6: 2804 | F6: 45755 | G6: 24920 | H6: 45815 | N6: Em aberto | O6: Nota fiscal do Sinistro Auto (Márcio Vieira), questionei via e-mail dia 16/06/25 - Fwd: PORTO SEGURO - NF 4802 - SYS4B
A7: Sys4B | B7: Atendimento | C7: 22/03/25 a 21/04/25 | D7: Sim | E7: 2838 | F7: 45783 | G7: 284824.47 | H7: 45843 | I7: INIBANK-54 Evoluções Salesforce para o Cartão e INIBANK-225 Evoluções Salesforce para a Conta Digital | J7: Cartão de Crédito Pessoa Física e Conta Digital PF | K7: Desenvolvimento no ambiente Salesforce Odin para melhorias de jornadas de atendimento para Cartão de Crédito Pessoa Física e Conta Digital PF | L7: Sim | N7: Em aberto | O7: Aprovado o pgto dia 11/06/25 via e-mail - Re: PORTO - NF 2838 - SYS4B
A8: Sys4B | B8: Atendimento | C8: 22/04/25 a 21/05/25 | D8: Sim | E8: 2886 | F8: 45811 | G8: 32224 | H8: 45871 | I8: INIBANK-54 Evoluções Salesforce para o Cartão e INIBANK-225 Evoluções Salesforce para a Conta Digital | J8: Cartão de Crédito Pessoa Física e Conta Digital PF | K8: Desenvolvimento no ambiente Salesforce Odin para melhorias de jornadas de atendimento para Cartão de Crédito Pessoa Física e Conta Digital PF | L8: Sim | N8: Em aberto | O8: NFe da frente da KITA - vide e-mail de 13/06/25 - Fwd: PORTO SEGURO - 2886 - SYS4B
A9: Sys4B | B9: Atendimento | C9: 22/04/25 a 21/05/25 | D9: Sim | E9: 2887 | F9: 45811 | G9: 283830.3 | H9: 45871 | I9: INIBANK-54 Evoluções Salesforce para o Cartão e INIBANK-225 Evoluções Salesforce para a Conta Digital | J9: Cartão de Crédito Pessoa Física e Conta Digital PF | K9: Desenvolvimento no ambiente Salesforce Odin para melhorias de jornadas de atendimento para Cartão de Crédito Pessoa Física e Conta Digital PF | L9: Sim | N9: Em aberto | O9: Aprovado o pgto dia 13/06/25 via e-mail - Fwd: PORTO - NF 2887 - SYS4B
A10: Capgemini | B10: Atendimento | C10: 01/01/25 a 31/01/25 | D10: Sim | E10: 145286 | F10: 45701 | G10: 131897.28 | H10: 45746 | I10: INIBANK-611 | J10: Cartão de Crédito Pessoa Jurídica e Conta Digital Pessoa Jurídica e Consórcio Pessoa Jurídica e Pessoa Física | K10: Desenvolvimento da jornadas de atendimento para Cartão de Crédito Pessoa Jurídica e Conta Digital Pessoa Jurídica na Plataforma Salesforce Odin e Desenvolvimento da jornadas de atendimento para o Consórcio Pessoa Jurídica e Pessoa Física na Plataforma Salesforce Odin | O10: Não há memória de cálculo, e não tenho a informação se foi aprovado ou se foi pago
A11: Capgemini | B11: Atendimento | C11: 01/02/25 a 28/02/25 | D11: Sim | E11: 145885 | F11: 45729 | G11: 88245.42 | H11: 45774 | I11: INIBANK-611 Implantação do SalesForce (ODIN) para Central de Atendimento | J11: Cartão de Crédito Pessoa Jurídica e Conta Digital Pessoa Jurídica | K11: Desenvolvimento da jornadas de atendimento para Cartão de Crédito Pessoa Jurídica e Conta Digital Pessoa Jurídica na Plataforma Salesforce Odin | O11: Marcos fez uma agenda dia 08/04 com a Vanessa para realizar a validação da NF. Não tenho informação sobre aprovação da NF e Pgto - vide e-mail de 07/04 - Re: NF(s) 145881 - PORTO_SEGURO_ADMINISTRADORA_DE_CONSORCIOS_LTDA
A12: Capgemini | B12: Atendimento | C12: 01/03/25 a 31/03/25 | D12: Sim | G12: R$ 146,501.52 | I12: INIBANK-226 Integração Consórcio (Newcon com Salesforce) | J12: Consórcio Pessoa Jurídica e Pessoa Física | K12: Desenvolvimento da jornadas de atendimento para o Consórcio Pessoa Jurídica e Pessoa Física na Plataforma Salesforce Odin | O12: Não tenho informações sobre pgto em aberto
A13: Capgemini | B13: Atendimento | C13: 01/03/25 a 31/03/25 | D13: Sim | G13: R$ 101,456.94 | I13: INIBANK-611 Implantação do SalesForce (ODIN) para Central de Atendimento | J13: Cartão de Crédito Pessoa Jurídica e Conta Digital Pessoa Jurídica | K13: Desenvolvimento da jornadas de atendimento para Cartão de Crédito Pessoa Jurídica e Conta Digital Pessoa Jurídica na Plataforma Salesforce Odin | O13: Não tenho informações sobre pgto em aberto
A14: Capgemini | B14: Atendimento | C14: 01/04/25 a 21/04/25 | D14: Sim | E14: 147368 | F14: 45789 | G14: 89693.94 | H14: 45834 | I14: INIBANK-226 Integração Consórcio (Newcon com Salesforce) | J14: Consórcio Pessoa Jurídica e Pessoa Física | K14: Desenvolvimento da jornadas de atendimento para o Consórcio Pessoa Jurídica e Pessoa Física na Plataforma Salesforce Odin | L14: Sim | N14: Em aberto | O14: Aprovado o pgto dia 12/06/25 via e-mail - Re: NF(s) 147368 - PORTO_SEGURO_ADMINISTRADORA_DE_CONSORCIOS_LTDA
A15: Capgemini | B15: Atendimento | C15: 01/04/25 a 21/04/25 | D15: Sim | E15: 147373 | F15: 45789 | G15: 77929.2 | H15: 45834 | I15: INIBANK-611 Implantação do SalesForce (ODIN) para Central de Atendimento | J15: Cartão de Crédito Pessoa Jurídica e Conta Digital Pessoa Jurídica | K15: Desenvolvimento da jornadas de atendimento para Cartão de Crédito Pessoa Jurídica e Conta Digital Pessoa Jurídica na Plataforma Salesforce Odin | L15: Sim | N15: Em aberto | O15: Aprovado o pgto dia 23/06/25 via e-mail - Re: NF(s) 147373 - PORTOSEG_SA_-_CREDITO,_FINANCIAMENTO_EINVESTIMENTO
A16: Capgemini | B16: Atendimento | C16: 22/04/25 a 21/05/25 | D16: Sim | E16: 148462 | F16: 45819 | G16: 121633.02 | H16: 45864 | I16: INIBANK-611 [Cartão PJ] Implantação do SalesForce (ODIN) para Central de Atendimento | J16: Cartão de Crédito Pessoa Jurídica e Conta Digital Pessoa Jurídica | K16: Desenvolvimento da jornadas de atendimento para Cartão de Crédito Pessoa Jurídica e Conta Digital Pessoa Jurídica na Plataforma Salesforce Odin | L16: Sim | N16: Em aberto | O16: Aprovado o pgto dia 11/06/25 via e-mail - NF(s) 148462 - PORTOSEG S A - CREDITO, FINANCIAMENTO EINVESTIMENTO
A17: Capgemini | B17: Atendimento | C17: 22/04/25 a 21/05/25 | D17: Sim | E17: 148457 | F17: 45819 | G17: 200222.04 | H17: 45864 | I17: INIBANK-226 Integração Consórcio (Newcon com Salesforce) | J17: Consórcio Pessoa Jurídica e Pessoa Física | K17: Desenvolvimento da jornadas de atendimento para o Consórcio Pessoa Jurídica e Pessoa Física na Plataforma Salesforce Odin | L17: Sim | N17: Em aberto | O17: Aprovado o pgto dia 11/06/25 via e-mail - NF(s) 148457 - PORTO SEGURO ADMINISTRADORA DE CONSORCIOS LTDA
A18: OSF Digital | B18: Atendimento | C18: 45717 | D18: Sim | E18: 763 | F18: 45755 | G18: 41333.04 | H18: 45785 | I18: INIBANK-611 [Cartão PJ] Implantação do SalesForce (ODIN) para Central de Atendimento | J18: Cartão de Crédito Pessoa Jurídica e Conta Digital Pessoa Jurídica | K18: Desenvolvimento da jornadas de atendimento para Cartão de Crédito Pessoa Jurídica e Conta Digital Pessoa Jurídica na Plataforma Salesforce Odin. Atuou na retirada das APIs Mocks nas jornadas de consumo das APIs do Iaas | L18: Sim | N18: Em aberto | O18: Não tenho informações sobre pgto em aberto
A19: OSF Digital | B19: Atendimento | C19: 22/04/25 a 21/05/25 | D19: Sim | E19: 883 | F19: 45818 | G19: 38556 | H19: 45848 | I19: INIBANK-611 [Cartão PJ] Implantação do SalesForce (ODIN) para Central de Atendimento | J19: Cartão de Crédito Pessoa Jurídica e Conta Digital Pessoa Jurídica | K19: Desenvolvimento da jornadas de atendimento para Cartão de Crédito Pessoa Jurídica e Conta Digital Pessoa Jurídica na Plataforma Salesforce Odin. Atuaram no desenvolvimento do front de atendimento para o cartão de crédito PJ | L19: Sim | N19: Em aberto | O19: Aprovado o pgto dia 16/06/25 via e-mail - ENC: PORTO SEGURO: Faturamento OSF Filial SP - Maio/2025 - Porto Bank / Atendimento-Consórcio - NF 883
A20: OSF Digital | B20: Atendimento | C20: 22/04/25 a 21/05/25 | D20: Sim | E20: 884 | F20: 45818 | G20: 54864.69 | H20: 45848 | I20: INIBANK-611 [Cartão PJ] Implantação do SalesForce (ODIN) para Central de Atendimento | J20: Cartão de Crédito Pessoa Jurídica e Conta Digital Pessoa Jurídica | K20: Desenvolvimento da jornadas de atendimento para Cartão de Crédito Pessoa Jurídica e Conta Digital Pessoa Jurídica na Plataforma Salesforce Odin. Atuou na retirada das APIs Mocks nas jornadas de consumo das APIs do Iaas | L20: Sim | N20: Em aberto | O20: Aprovado o pgto dia 16/06/25 via e-mail - ENC: PORTO SEGURO: Faturamento OSF - Maio/2025 - Porto Bank - Segmento PJ - NF 884
A21: Sensedia | B21: Parcerias | C21: 45717 | D21: Sim | E21: 28622 | F21: 45726 | G21: 37432.03 | H21: 45757 | J21: Parcerias Pessoa Jurídica | O21: Recebi esta NFe da Gabi Simiano no chat no dia 13/06/2025
A22: ACT Digital | B22: Atendimento | C22: 45778 | D22: Sim | E22: 80531 | F22: 45817 | G22: 23016 | H22: 45877 | I22: INIBANK-289 - [Sustentação] Parcerias, Atendimento e Esteiras | J22: Sustentação | K22: Sustentação das frentes de Parcerias, Atendimento e Esteiras. Alocação do João Henrique Fonseca Vieira da Silva. Fase Execução-Produto: Parcerias | L22: Sim | N22: Em aberto | O22: Aprovado o pgto dia 16/06/25 via e-mail - Fwd: act digital | Porto Seguro | Medição dos Serviços Prestados | Área: Portal | 22/04/2025 a 21/05/2025 | Marcos Rosa
A23: Capgemini | B23: Atendimento | C23: 22/05/25 a 21/06/25 | D23: Sim | E23: 149204 | F23: 45846 | G23: 115880.7 | H23: 45891 | I23: INIBANK-611 [Cartão PJ] Implantação do SalesForce (ODIN) para Central de Atendimento | J23: Cartão de Crédito Pessoa Jurídica e Conta Digital Pessoa Jurídica | K23: Desenvolvimento da jornadas de atendimento para Cartão de Crédito Pessoa Jurídica e Conta Digital Pessoa Jurídica na Plataforma Salesforce Odin. Atuou na retirada das APIs Mocks nas jornadas de consumo das APIs do Iaas | L23: Sim | N23: Em aberto | O23: Aprovado o pgto dia 08/07/25 via e-mail - NF(s) 149204 - PORTOSEG S/A - CREDITO, FINANCIAMENTO EINVESTIMENTO
